<?xml version="1.0" encoding="UTF-8"?>

<!-- 
 * PopulateDatabase.xml
 *
 * Copyright (C) 2018 Universidad de Sevilla
 * 
 * The use of this project is hereby constrained to the conditions of the 
 * TDG Licence, a copy of which you may download from 
 * http://www.tdg-seville.info/License.html
 -->

<beans xmlns="http://www.springframework.org/schema/beans"
	xmlns:xsi="http://www.w3.org/2001/XMLSchema-instance"
	xsi:schemaLocation="
		http://www.springframework.org/schema/beans http://www.springframework.org/schema/beans/spring-beans.xsd
	">
	
	<!-- Date formats -->
	
	<bean id="completeDateFormat" class="java.text.SimpleDateFormat">
    	<constructor-arg value="dd/MM/yyyy HH:mm:ss"/>
	</bean>
	
	<!-- User accounts -->

	<bean id="userAccount1" class="security.UserAccount">
		<property name="username" value="admin" />
		<property name="password" value="21232f297a57a5a743894a0e4a801fc3" />
		<property name="authorities">
			<list>
				<bean class="security.Authority">
					<property name="authority" value="ADMIN" />
				</bean>
			</list>
		</property>
	</bean>

	<bean id="userAccount2" class="security.UserAccount">
		<property name="username" value="customer" />
		<property name="password" value="91ec1f9324753048c0096d036a694f86" />
		<property name="authorities">
			<list>
				<bean class="security.Authority">
					<property name="authority" value="CUSTOMER" />
				</bean>
			</list>
		</property>
	</bean>

	<bean id="userAccount3" class="security.UserAccount">
		<property name="username" value="super" />
		<property name="password" value="1b3231655cebb7a1f783eddf27d254ca" />
		<property name="authorities">
			<list>
				<bean class="security.Authority">
					<property name="authority" value="ADMIN" />
				</bean>
				<bean class="security.Authority">
					<property name="authority" value="CUSTOMER" />
				</bean>
			</list>
		</property>
	</bean>
	
		<bean id="userAccount4" class="security.UserAccount">
		<property name="username" value="customer" />
		<property name="password" value="91ec1f9324753048c0096d036a694f86" />
		<property name="authorities">
			<list>
				<bean class="security.Authority">
					<property name="authority" value="CUSTOMER" />
				</bean>
			</list>
		</property>
	</bean>
	
	<bean id="userAccount5" class="security.UserAccount">
		<property name="username" value="customer" />
		<property name="password" value="91ec1f9324753048c0096d036a694f86" />
		<property name="authorities">
			<list>
				<bean class="security.Authority">
					<property name="authority" value="CUSTOMER" />
				</bean>
			</list>
		</property>
	</bean>
	
	<bean id="userAccount6" class="security.UserAccount">
		<property name="username" value="customer" />
		<property name="password" value="91ec1f9324753048c0096d036a694f86" />
		<property name="authorities">
			<list>
				<bean class="security.Authority">
					<property name="authority" value="CUSTOMER" />
				</bean>
			</list>
		</property>
	</bean>
	
	
	<bean id="userAccount7" class="security.UserAccount">
		<property name="username" value="handywoker" />
		<property name="password" value="24da2ce4fb8a46c3d44d2c72305a31a2" />
		<property name="authorities">
			<list>
				<bean class="security.Authority">
					<property name="authority" value="HANDYWORKER" />
				</bean>
			</list>
		</property>
	</bean>
	
	
	<bean id="userAccount8" class="security.UserAccount">
		<property name="username" value="handywoker" />
		<property name="password" value="24da2ce4fb8a46c3d44d2c72305a31a2" />
		<property name="authorities">
			<list>
				<bean class="security.Authority">
					<property name="authority" value="HANDYWORKER" />
				</bean>
			</list>
		</property>
	</bean>
	
	
	<bean id="userAccount9" class="security.UserAccount">
		<property name="username" value="handywoker" />
		<property name="password" value="24da2ce4fb8a46c3d44d2c72305a31a2" />
		<property name="authorities">
			<list>
				<bean class="security.Authority">
					<property name="authority" value="HANDYWORKER" />
				</bean>
			</list>
		</property>
	</bean>
	
	
	<bean id="userAccount10" class="security.UserAccount">
		<property name="username" value="handywoker" />
		<property name="password" value="24da2ce4fb8a46c3d44d2c72305a31a2" />
		<property name="authorities">
			<list>
				<bean class="security.Authority">
					<property name="authority" value="HANDYWORKER" />
				</bean>
			</list>
		</property>
	</bean>
	
	
	
	
	<!-- Other domain beans come here -->	
	
	<!-- Administrators -->
	
	<bean id="administrator1" class="domain.Administrator">
		<property name="name" value="Mario" />
		<property name="middleName" value="Xavier" />
		<property name="surname" value="García" />
	    <property name="photo" value="https://cdn.pixabay.com/photo/2017/06/26/02/47/people-2442565_960_720.jpg" />
		<property name="email" value="maxagar@gmail.com" />
		<property name="phone" value="+34(456)123456789" />
	    <property name="address" value="C/Calle, 32" />
		<property name="banned" value="false" />
		<property name="suspicious" value="false" />
		<property name="sendedMessages">
			<list>
				<ref bean="sendedMessage1Admin1" />
				<ref bean="sendedMessage2Admin1" />
				<ref bean="sendedMessage3Admin1" />
			</list>
		</property>
		<property name="receivedMessages">
			<list>
				<ref bean="sendedMessage1Admin2" />
				<ref bean="sendedMessage2Admin2" />
				<ref bean="sendedMessage3Admin2" />
			</list>
		</property>
		<property name="folders">
			<list>
				<ref bean="folder1Admin1" />
				<ref bean="folder2Admin1" />
				<ref bean="folder3Admin1" />
				<ref bean="folder4Admin1" />
			</list>
		</property>
	    <property name="socialProfiles">
	    	<list>
	    		<ref bean="socialProfile1Admin1" />
	    		<ref bean="socialProfile2Admin1" />
	    	</list>
	    </property>
		<property name="userAccount" ref="userAccountAdmin1" />
		<property name="curriculum" ref="curriculumAdmin1" />
	</bean>
	
	<bean id="administrator2" class="domain.Administrator">
		<property name="name" value="Clara" />
		<property name="surname" value="Prats" />
		<property name="email" value="maxagar@gmail.com" />
		<property name="banned" value="false" />
		<property name="suspicious" value="false" />
		<property name="sendedMessages">
			<list/>
		</property>
		<property name="receivedMessages">
			<list/>
		</property>
		<property name="folders">
			<list>
				<ref bean="folder1Admin2" />
				<ref bean="folder2Admin2" />
				<ref bean="folder3Admin2" />
				<ref bean="folder4Admin2" />
			</list>
		</property>
	    <property name="socialProfiles">
	    	<list/>
	    </property>
		<property name="userAccount" ref="userAccountAdmin2" />
	</bean>
	
	<!-- Application -->
	
	<bean id="application1" class="domain.Application">
		<property name="price" value="3.14"/>
	    <property name="moment">
	    	<bean id="momentApplication1" factory-bean="completeDateFormat" factory-method="parse">
    			<constructor-arg value="28/10/2017 23:59:59" />
			</bean>
	    </property>
		<property name="status" value="PENDING" />
		<property name="workerComments" value="I work hard" />
		<property name="handyWorker" ref="handyWorker1" />
		<property name="fixupTask" ref="fixupTask1" />
	</bean>
	
	<bean id="application2" class="domain.Application">
		<property name="price" value="12.34"/>
	    <property name="moment">
	    	<bean id="momentApplication2" factory-bean="completeDateFormat" factory-method="parse">
    			<constructor-arg value="31/10/2018 00:00:00" />
			</bean>
	    </property>
		<property name="status" value="ACCEPTED" />
		<property name="workerComments" value="I work very hard" />
		<property name="customerComments" value="OK" />
		<property name="creditCard">
			<bean name="creditCardApplication2" class="domain.CreditCard">
				<property name="holderName" value="Paco Pepe Pérez" />
				<property name="brandName" value="VISA" />
				<property name="number" value="4556042640541332" />
				<property name="expirationDate" >
					<bean id="expirationDateCreditCard2" factory-bean="completeDateFormat" factory-method="parse">
    					<constructor-arg value="28/10/2020 23:59:59" />
					</bean>
				</property>
				<property name="cvvCode" value="452" />
			</bean>
		</property>
		<property name="handyWorker" ref="handyWorker1" />
		<property name="fixupTask" ref="fixupTask2" />
	</bean>
	
	<bean id="application3" class="domain.Application">
		<property name="price" value="10.43"/>
	    <property name="moment" value="15:56:03" >
	    	<bean id="momentApplication3" factory-bean="completeDateFormat" factory-method="parse">
    			<constructor-arg value=""/>
			</bean>
	    </property>
		<property name="status" value="REJECTED" />
		<property name="handyWorker" ref="handyWorker2" />
		<property name="fixupTask" ref="fixupTask2" />
	</bean>
	
	<!-- Categories -->
	
	<bean id="categoryRoot">
		<property name="name" value="ROOT" />
		<property name="fixupTasks">
			<list/>
		</property>
		<property name="childsCategories">
			<list/>
		</property>
	    <property name="parentCategory" ref="categoryRoot" />
	</bean>
	
	<bean id="categoryCarpentry">
		<property name="name" value="Carpentry" />
		<property name="fixupTasks">
			<list/>
		</property>
		<property name="childsCategories">
			<list/>
		</property>
	    <property name="parentCategory" ref="categoryRoot" />
	</bean> 
	
	<bean id="categoryCeilingRepair">
		<property name="name" value="CeilingRepair" />
		<property name="fixupTasks">
			<list/>
		</property>
		<property name="childsCategories">
			<list/>
		</property>
	    <property name="parentCategory" ref="categoryConcreteWork" />
	</bean>
	
	<bean id="categoryCleaning">
		<property name="name" value="Cleaning" />
		<property name="fixupTasks">
			<list/>
		</property>
		<property name="childsCategories">
			<list/>
		</property>
	    <property name="parentCategory" ref="categoryRoot" />
	</bean> 
	
	<bean id="categoryConcreteWork">
		<property name="name" value="ConcreteWork" />
		<property name="fixupTasks">
			<list/>
		</property>
		<property name="childsCategories">
			<list/>
		</property>
	    <property name="parentCategory" ref="categoryRoot" />
	</bean>
	
	<bean id="categoryDoors">
		<property name="name" value="Carpentry" />
		<property name="fixupTasks">
			<list/>
		</property>
		<property name="childsCategories">
			<list/>
		</property>
	    <property name="parentCategory" ref="categoryCarpentry" />
	</bean> 
	
	<bean id="categoryElectricalWiring">
		<property name="name" value="ElectricalWiring" />
		<property name="fixupTasks">
			<list/>
		</property>
		<property name="childsCategories">
			<list/>
		</property>
	    <property name="parentCategory" ref="categoryRoot" />
	</bean>
	
	<bean id="categoryFanInstallation">
		<property name="name" value="FanInstallation" />
		<property name="fixupTasks">
			<list/>
		</property>
		<property name="childsCategories">
			<list/>
		</property>
	    <property name="parentCategory" ref="categoryElectricalWiring" />
	</bean>
	
	<bean id="categoryFenceFixing">
		<property name="name" value="FenceFixing" />
		<property name="fixupTasks">
			<list/>
		</property>
		<property name="childsCategories">
			<list/>
		</property>
	    <property name="parentCategory" ref="categoryHomeSecuritySystems" />
	</bean>
	
	<bean id="categoryHomeSecuritySystems">
		<property name="name" value="HomeSecuritySystems" />
		<property name="fixupTasks">
			<list/>
		</property>
		<property name="childsCategories">
			<list/>
		</property>
	    <property name="parentCategory" ref="categoryRoot" />
	</bean>
	
	<bean id="categoryInsulationInstallation">
		<property name="name" value="InsulationInstallation" />
		<property name="fixupTasks">
			<list/>
		</property>
		<property name="childsCategories">
			<list/>
		</property>
	    <property name="parentCategory" ref="categoryRoot" />
	</bean>
	
	<bean id="categoryLampRepairs">
		<property name="name" value="LampRepairs" />
		<property name="fixupTasks">
			<list/>
		</property>
		<property name="childsCategories">
			<list/>
		</property>
	    <property name="parentCategory" ref="categoryElectricalWiring" />
	</bean>
	
	<bean id="categoryMoving">
		<property name="name" value="Moving" />
		<property name="fixupTasks">
			<list/>
		</property>
		<property name="childsCategories">
			<list/>
		</property>
	    <property name="parentCategory" ref="categoryRoot" />
	</bean>
	
	<bean id="categoryPainting">
	
	</bean>
	
	<bean id="categoryPestControl">
		<property name="name" value="PestControl" />
		<property name="fixupTasks">
			<list/>
		</property>
		<property name="childsCategories">
			<list/>
		</property>
	    <property name="parentCategory" ref="categoryCleaning" />
	</bean>
	
	<bean id="categoryPlumbingRepairs">
		<property name="name" value="SolarPanels" />
		<property name="fixupTasks">
			<list/>
		</property>
		<property name="childsCategories">
			<list/>
		</property>
	    <property name="parentCategory" ref="categoryRoot" />
	</bean>
	
	<bean id="categoryRoofing">
		<property name="name" value="Roofing" />
		<property name="fixupTasks">
			<list/>
		</property>
		<property name="childsCategories">
			<list/>
		</property>
	    <property name="parentCategory" ref="categoryConcreteWork" />
	</bean>
	
	<bean id="categoryShelfInstallation">
		<property name="name" value="ShelfInstallation" />
		<property name="fixupTasks">
			<list/>
		</property>
		<property name="childsCategories">
			<list>
				
			</list>
		</property>
	    <property name="parentCategory" ref="categoryCarpentry" />
	</bean>
	
	<bean id="categorySolarPanels">
		<property name="name" value="SolarPanels" />
		<property name="fixupTasks">
			<list/>
		</property>
		<property name="childsCategories">
			<list/>
		</property>
	    <property name="parentCategory" ref="categoryElectricalWiring" />
	</bean>
	
	<bean id="categorySoundProofing">
		<property name="name" value="SoundProofing" />
		<property name="fixupTasks">
			<list/>
		</property>
		<property name="childsCategories">
			<list/>
		</property>
	    <property name="parentCategory" ref="categoryInsulationInstallation" />
	</bean>
	
	<bean id="categorySprinklerRepair">
		<property name="name" value="SprinklerRepair" />
		<property name="fixupTasks">
			<list/>
		</property>
		<property name="childsCategories">
			<list/>
		</property>
	    <property name="parentCategory" ref="categoryElectricalWiring" />
	</bean>
	
	<bean id="categoryWindowRepair">
		<property name="name" value="WindowRepair" />
		<property name="fixupTasks">
			<list/>
		</property>
		<property name="childsCategories">
			<list/>
		</property>
	    <property name="parentCategory" ref="categoryCarpentry" />
	</bean>
	
	<!-- Complaints -->
	
	<bean id="complaint1" class="domain.Complaint" >
		<property name="ticker" value="181103-RTIB32" />
		<property name="moment">
			<bean id="momentComplaint1" factory-bean="completeDateFormat" factory-method="parse">
    			<constructor-arg value="03/11/2018 23:59:59" />
			</bean>
		</property>
	    <property name="description" value="This fix is a fake" />
	    <property name="attachments">
	    	<list>
	    		<value>https://trello-attachments.s3.amazonaws.com/5bdc2fda6f3ec4653ca5ca0e/5bdc38d6221aa411081293c9/0fd144293b39a447a86f3586caa178ac/Acme_Handy_Worker.pdf</value>
	    		<value>https://github.com/DP1819/D03/tree/master/src/main</value>
	    	</list>
	    </property>
		<property name="report" ref="report1" />
		<property name="fixuptask" ref="fixupTask1" />
	    <property name="referee" ref="referee1" />
	</bean>
	
	<bean id="complaint2" class="domain.Complaint" >
		<property name="ticker" value="181103-43ION6" />
		<property name="moment">
			<bean id="momentComplaint2" factory-bean="completeDateFormat" factory-method="parse">
    			<constructor-arg value="03/11/2018 23:59:59" />
			</bean>
		</property>
	    <property name="description" value="This fix is a fake" />
	    <property name="attachments">
	    	<list/>
	    </property>
		<property name="fixuptask" ref="fixupTask2" />
	</bean>
	
	<!-- Curricula -->
	
	<bean id="curriculum1" class="domain.Curriculum">
		<property name="ticker" value="181101-AC34DF" />
		<property name="handyWorker" ref="handyWorker1" />
		<property name="personalRecord" ref="personalRecord1" />
		<property name="educationRecords">
			<list/>
		</property>
	    <property name="profesionalRecords">
	    	<list/>
	    </property>
	    <property name="endorserRecords">
	    	<list/>
	    </property>
		<property name="miscellaneousRecords">
			<list/>
		</property>
	</bean>
	
	<bean id="curriculum2" class="domain.Curriculum">
		<property name="ticker" value="180321-ALONSO" />
		<property name="handyWorker" ref="handyWorker2" />
		<property name="personalRecord" ref="personalRecord2" />
		<property name="educationRecords">
			<list/>
		</property>
	    <property name="profesionalRecords">
	    	<list/>
	    </property>
	    <property name="endorserRecords">
	    	<list/>
	    </property>
		<property name="miscellaneousRecords">
			<list/>
		</property>
	</bean>
	
	<bean id="curriculum3" class="domain.Curriculum">
		<property name="ticker" value="170730-F24RAN" />
		<property name="handyWorker" ref="handyWorker3" />
		<property name="personalRecord" ref="personalRecord3" />
		<property name="educationRecords">
			<list/>
		</property>
	    <property name="profesionalRecords">
	    	<list/>
	    </property>
	    <property name="endorserRecords">
	    	<list/>
	    </property>
		<property name="miscellaneousRecords">
			<list/>
		</property>
	</bean>
	
	<bean id="curriculum4" class="domain.Curriculum">
		<property name="ticker" value="101010-987321" />
		<property name="handyWorker" ref="handyWorker4" />
		<property name="personalRecord" ref="personalRecord4" />
		<property name="educationRecords">
			<list/>
		</property>
	    <property name="profesionalRecords">
	    	<list/>
	    </property>
	    <property name="endorserRecords">
	    	<list/>
	    </property>
		<property name="miscellaneousRecords">
			<list/>
		</property>
	</bean>
	
	<!-- ___________________Customers___________________________________-->
	<bean id="customer1" class="domain.Customer">
		<property name="name" value="Alfonso"></property>
		<property name="middleName" value="HackerMan"></property>
		<property name="surname" value="Alarcon"></property>
		<property name="photo"
			value="https://cdn.pixabay.com/user/2015/01/20/20-56-42-330_250x250.jpg"></property>
		<property name="email" value="uncorreonormal@hotmail.com"></property>
		<property name="phone" value="658225856"></property>
		<property name="address" value="C/ sal y arena"></property>
		<property name="banned" value="false"></property>
		<property name="suspicious" value="false"></property>
		
		
		<property name="userAccount" ref="userAccount2">
		</property>
		
		<property name="socialProfiles">
			<list>
				<ref bean="socialProfile1"></ref>
			</list>
		</property>

		<property name="folders">
			<list>
				<ref bean="folder1" />
				<ref bean="folder2" />
				<ref bean="folder3" />
				<ref bean="folder4" />
			</list>
		</property>
		<property name="messages">
			<list>
			</list>
		</property>

	</bean>
	
	<bean id="customer2" class="domain.Customer">
		<property name="name" value="Pablo"></property>
		<property name="middleName" value="HackerBoy"></property>
		<property name="surname" value="Pino"></property>
		<property name="photo"
			value="https://cdn.pixabay.com/user/2015/01/20/20-56-42-330_250x250.jpg"></property>
		<property name="email" value="uncorreomaslargo@hotmail.com"></property>
		<property name="phone" value="655525856"></property>
		<property name="address" value="C/ esperanza de rafael"></property>
		<property name="banned" value="false"></property>
		<property name="suspicious" value="false"></property>
		
		<property name="userAccount" ref="userAccount4">
		</property>
		
		<property name="socialProfiles">
			<list>
				<ref bean="socialProfile2"></ref>
			</list>
		</property>
			

		<property name="folders">
			<list>
				<ref bean="folder5" />
				<ref bean="folder6" />
				<ref bean="folder7" />
				<ref bean="folder8" />
			</list>
		</property>
		<property name="messages">
			<list>
			</list>
		</property>

	</bean>
	
	<bean id="customer3" class="domain.Customer">
		<property name="name" value="Juan"></property>
		<property name="middleName" value=""></property>
		<property name="surname" value="De la Aceituna"></property>
		<property name="photo"
			value="https://cdn.pixabay.com/user/2015/01/20/20-56-42-330_250x250.jpg"></property>
		<property name="email" value="juandelaaceitunaynooliva@hotmail.com"></property>
		<property name="phone" value="674525856"></property>
		<property name="address" value="C/ Perdida de la mano de Dios"></property>
		<property name="banned" value="false"></property>
		<property name="suspicious" value="false"></property>
		
		<property name="userAccount" ref="userAccount5">
		</property>
		
		<property name="socialProfiles">
			<list>
				<ref bean="socialProfile3"></ref>
			</list>
		</property>

		<property name="folders">
			<list>
				<ref bean="folder9" />
				<ref bean="folder10" />
				<ref bean="folder11" />
				<ref bean="folder12" />
			</list>
		</property>
		<property name="messages">
			<list>
			</list>
		</property>

	</bean>
	
	<bean id="customer4" class="domain.Customer">
		<property name="name" value="Elena"></property>
		<property name="middleName" value="TomasLena"></property>
		<property name="surname" value="Molina"></property>
		<property name="photo"
			value="https://cdn.pixabay.com/user/2015/01/20/20-56-42-330_250x250.jpg"></property>
		<property name="email" value="tomaslena@hotmail.com"></property>
		<property name="phone" value="677525856"></property>
		<property name="address" value="C/ pasada la estacion del ave"></property>
		<property name="banned" value="false"></property>
		<property name="suspicious" value="false"></property>
		
		<property name="userAccount" ref="userAccount6">
		</property>
		
		<property name="socialProfiles">
			<list>
			</list>
		</property>

		<property name="folders">
			<list>
				<ref bean="folder13" />
				<ref bean="folder14" />
				<ref bean="folder15" />
				<ref bean="folder16" />
			</list>
		</property>
		<property name="messages">
			<list>
			</list>
		</property>

	</bean>
	
	
	<!-- ___________________Education Records___________________________________-->
	<bean id="educationRecord1" class="domain.EducationRecord">
		<property name="diplomaTitle" value="Bachillerato"></property>
		<property name="start" value="February 6, 2010 09:30"></property>
		<property name="end" value="May 29, 2012 15:00"></property>
		<property name="institution" value="Academia Preuniversitaria"></property>
		<property name="attachment"
			value="https://www.lifewire.com/thmb/-h08oONgxcBRcaYOTiMuJd8ogVU=/768x0/filters:no_upscale():max_bytes(150000):strip_icc()/GettyImages-469187056-57cdf0a45f9b5829f4457c9a.jpg"></property>
		<property name="comments" value="Un cinco pelao he sacao."></property>
		
		<property name="curriculum" ref="curriculum1"></property>

		
	</bean>
	
	<bean id="educationRecord2" class="domain.EducationRecord">
		<property name="diplomaTitle" value="Bachillerato"></property>
		<property name="start" value="February 22, 2010 09:30"></property>
		<property name="end" value="May 29, 2012 15:02"></property>
		<property name="institution" value="Academia militar"></property>
		<property name="attachment"
			value="https://www.lifewire.com/thmb/-h08oONgxcBRcaYOTiMuJd8ogVU=/768x0/filters:no_upscale():max_bytes(150000):strip_icc()/GettyImages-469187056-57cdf0a45f9b5829f4457c9a.jpg"></property>
		<property name="comments" value="He peloteado que da gusto."></property>
		
		<property name="curriculum" ref="curriculum2"></property>
		
	
	</bean>
	
	<bean id="educationRecord3" class="domain.EducationRecord">
		<property name="diplomaTitle" value="ESO"></property>
		<property name="start" value="December 12, 2014 19:30"></property>
		<property name="end" value="May 29, 2016 15:02"></property>
		<property name="institution" value="Academia eclesiastica Satanas por aqui no vengas mas"></property>
		<property name="attachment"
			value="https://www.lifewire.com/thmb/-h08oONgxcBRcaYOTiMuJd8ogVU=/768x0/filters:no_upscale():max_bytes(150000):strip_icc()/GettyImages-469187056-57cdf0a45f9b5829f4457c9a.jpg"></property>
		<property name="comments" value="Cuidado con los curas"></property>
		
		<property name="curriculum" ref="curriculum3"></property>
		
	</bean>
	
	
	<bean id="educationRecord4" class="domain.EducationRecord">
		<property name="diplomaTitle" value="ESO"></property>
		<property name="start" value="December 15, 2013 09:30"></property>
		<property name="end" value="May 29, 2016 15:02"></property>
		<property name="institution" value="Academia Satanica Satanas por aqui no ven mas"></property>
		<property name="attachment"
			value="https://www.lifewire.com/thmb/-h08oONgxcBRcaYOTiMuJd8ogVU=/768x0/filters:no_upscale():max_bytes(150000):strip_icc()/GettyImages-469187056-57cdf0a45f9b5829f4457c9a.jpg"></property>
		<property name="comments" value="Cuidado con los fanaticos de satanas"></property>
		
		<property name="curriculum" ref="curriculum4"></property>
		
	</bean>
	
	<!-- ___________________Endorsers Records___________________________________-->
	<bean id="endorserRecord1" class="domain.EndorserRecord">
		<property name="fullName" value="Lipasam"></property>
		<property name="photo" value="https://cdn.pixabay.com/user/2015/01/20/20-56-42-330_250x250.jpg"></property>
		<property name="email" value="lipasam@gmail.es"></property>
		<property name="phone" value="954586598"></property>
		<property name="linkedProfile" value="http://www.linkedin.com/in/lipasam"></property>
		
		
		<property name="curriculum" ref="curriculum1"></property>
		
	</bean>
	
		<bean id="endorserRecord2" class="domain.EndorserRecord">
		<property name="fullName" value="Emasesa"></property>
		<property name="photo" value="https://cdn.pixabay.com/user/2015/01/20/20-56-42-330_250x250.jpg"></property>
		<property name="email" value="Emasesa@gmail.es"></property>
		<property name="phone" value="957586598"></property>
		<property name="linkedProfile" value="http://www.linkedin.com/in/emasesa"></property>
		
		
		<property name="curriculum" ref="curriculum2"></property>
		
	</bean>
	
			<bean id="endorserRecord3" class="domain.EndorserRecord">
		<property name="fullName" value="Vips"></property>
		<property name="photo" value="https://cdn.pixabay.com/user/2015/01/20/20-56-42-330_250x250.jpg"></property>
		<property name="email" value="vips@gmail.es"></property>
		<property name="phone" value="957456598"></property>
		<property name="linkedProfile" value="http://www.linkedin.com/in/emasesa"></property>
		
		
		<property name="curriculum" ref="curriculum3"></property>
		
	</bean>
	
			<bean id="endorserRecord2" class="domain.EndorserRecord">
		<property name="fullName" value="Disney"></property>
		<property name="photo" value="https://cdn.pixabay.com/user/2015/01/20/20-56-42-330_250x250.jpg"></property>
		<property name="email" value="disneyfantasy@gmail.es"></property>
		<property name="phone" value="954571258"></property>
		<property name="linkedProfile" value="http://www.linkedin.com/in/disney"></property>
		
		
		<property name="curriculum" ref="curriculum4"></property>
		
	</bean>
	
	<!-- ___________________Finders __________________________________-->
	<bean id="finder1" class="domain.Finder">
		<property name="keyword" value="cocina"></property>
		<property name="maxPrice" value="1200.0"></property>
		<property name="minPrice" value="2200.0"></property>
		
	</bean>

	<bean id="finder2" class="domain.Finder">
		<property name="keyword" value="salon"></property>
		<property name="minimumDate" value="May 1, 2019 12:00"></property>
		<property name="maximumDate" value="June 25, 2019 21:00"></property>
	</bean>
	
		<bean id="finder3" class="domain.Finder">
		<property name="keyword" value="azulejo"></property>
		<property name="maxPrice" value="200.0"></property>
		<property name="minPrice" value="800.0"></property>
		<property name="minimumDate" value="February 12, 2019 12:00"></property>
		<property name="maximumDate" value="June 25, 2019 21:00"></property>
	</bean>
	
	<bean id="finder4" class="domain.Finder">
		<property name="maxPrice" value="200.0"></property>
		<property name="minPrice" value="2000.0"></property>

	</bean>
	
	<!-- ___________________Endorsable__________________________________-->
	<bean id="endorsable1" class="domain.Endorsable">
		<property name="score" value="0.75"></property>
		<property name="endorsements">
			<list>
				<ref bean="endorsement1"></ref>
			</list>
		</property>
		
	</bean>
	
	<bean id="endorsable2" class="domain.Endorsable">
		<property name="score" value="-0.75"></property>
		<property name="endorsements">
			<list>
				<ref bean="endorsement2"></ref>
			</list>
		</property>
		
	</bean>
	
	<bean id="endorsable3" class="domain.Endorsable">
		<property name="score" value="0.25"></property>
		<property name="endorsements">
			<list>
				<ref bean="endorsement3"></ref>
			</list>
		</property>
		
	</bean>
	
	<bean id="endorsable4" class="domain.Endorsable">
		<property name="score" value="0.35"></property>
		<property name="endorsements">
			<list>
				<ref bean="endorsement4"></ref>
			</list>
		</property>
		
	</bean>
	
	
	<!-- ___________________Endorsement__________________________________-->
	<bean id="endorsement1" class="domain.Endorsement">
		<property name="moment" value="February 12, 2017 12:00"></property>
		<property name="comments" value="Estoy muy contenta"></property>
		<property name="sender" ref="endorsable1"></property>
		<property name="receiver" ref="endorsable2"></property>
		
	</bean>
	
	<bean id="endorsement2" class="domain.Endorsement">
		<property name="moment" value="February 12, 2016 12:00"></property>
		<property name="comments" value="NO estoy muy contenta"></property>
		<property name="sender" ref="endorsable2"></property>
		<property name="receiver" ref="endorsable3"></property>
		
	</bean>
	
	<bean id="endorsement3" class="domain.Endorsement">
		<property name="moment" value="January 22, 2016 22:00"></property>
		<property name="comments" value="nada que añadir por aqui"></property>
		<property name="sender" ref="endorsable3"></property>
		<property name="receiver" ref="endorsable4"></property>
		
	</bean>
	
	<bean id="endorsement4" class="domain.Endorsement">
		<property name="moment" value="December 22, 2017 22:10"></property>
		<property name="comments" value="estoy muy descontento y lo pongo aqui"></property>
		<property name="sender" ref="endorsable4"></property>
		<property name="receiver" ref="endorsable1"></property>
		
	</bean>
	
	<!-- Sponsor -->

	<bean id="sponsor1" class="domain.Sponsor">
		
		<property name="sponsorships">
			<list>
				<ref bean="sponsorship1" />
				<ref bean="sponsorship2" />	
			</list>
		</property>
	</bean>
	
	
	<bean id="sponsor2" class="domain.Sponsor">
		
		<property name="sponsorships">
			<list>
				<ref bean="sponsorship1" />
				<ref bean="sponsorship2" />	
			</list>
		</property>
	</bean>
	
	
	<bean id="sponsor3" class="domain.Sponsor">
		
		<property name="sponsorships">
			<list>
				<ref bean="sponsorship1" />
				<ref bean="sponsorship3" />	
			</list>
		</property>
	</bean>
	
	
	<!-- Sponsorships -->
	

	<bean id="sponsorship1" class="domain.Sponsor">
	
		<property name="banner" value="http://www.banner.com" />
		<property name="page" value="http://www.page.com" />
		<property name="creditCard" value="4111111111111111" />
		<property name="sponsor" value="Juan Manuel Aceituna" />
		<property name="tutorials">
			<list>
				<ref bean="tutorial1" />
				<ref bean="tutorial2" />	
			</list>
		</property>
	</bean>
	
	<bean id="sponsorship2" class="domain.Sponsor">
	
		<property name="banner" value="http://www.banner2.com" />
		<property name="page" value="http://www.page2.com" />
		<property name="creditCard" value="5111111111111111" />
		<property name="sponsor" value="Alfonso Aceituna" />
		<property name="tutorials">
			<list>
				<ref bean="tutorial1" />
				<ref bean="tutorial2" />	
			</list>
		</property>
	</bean>
	
	<bean id="sponsorship3" class="domain.Sponsor">
	
		<property name="banner" value="http://www.banner3.com" />
		<property name="page" value="http://www.page3.com" />
		<property name="creditCard" value="6111111111111111" />
		<property name="sponsor" value="Elena SinAnchoa" />
		<property name="tutorials">
			<list>
				<ref bean="tutorial1" />
				<ref bean="tutorial3" />	
			</list>
		</property>
	</bean>
	
	<!-- Tutorial -->

	<bean id="tutorial1" class="domain.Tutorial">
	
		<property name="moment" value="02/09/2009" />
		<property name="title" value="Como entrenar a tu dragon" />
		<property name="summary" value="Como se entrenan los dragones" />
		<property name="handyWorker" value="Juan Manuel Aceituna" />
		<property name="pictures">
			<list>
				<ref bean="picture1" />
				<ref bean="picture2" />	
			</list>
		</property>
		
		<property name="sections">
			<list>
				<ref bean="section1" />
				<ref bean="section2" />	
			</list>
		</property>
		
		<property name="sponsorships">
			<list>
				<ref bean="sponsorship1" />
				<ref bean="sponsorship2" />	
			</list>
		</property>
	</bean>
	
	
	<bean id="tutorial2" class="domain.Tutorial">
	
		<property name="moment" value="12/09/2009" />
		<property name="title" value="Como entrenar a tu dragon 2" />
		<property name="summary" value="Como se entrenan los dragones 2" />
		<property name="handyWorker" value="Poncho Aceituna" />
		<property name="pictures">
			<list>
				<ref bean="picture1" />
				<ref bean="picture2" />	
			</list>
		</property>
		
		<property name="sections">
			<list>
				<ref bean="section1" />
				<ref bean="section2" />	
			</list>
		</property>
		
		<property name="sponsorships">
			<list>
				<ref bean="sponsorship1" />
				<ref bean="sponsorship3" />	
			</list>
		</property>
	</bean>
	
	<bean id="tutorial3" class="domain.Tutorial">
	
		<property name="moment" value="02/09/2011" />
		<property name="title" value="Como entrenar a tu dragon 3" />
		<property name="summary" value="Como se entrenan los dragones 3" />
		<property name="handyWorker" value="Elena Aceituna" />
		<property name="pictures">
			<list>
				<ref bean="picture1" />
				<ref bean="picture2" />	
			</list>
		</property>
		
		<property name="sections">
			<list>
				<ref bean="section1" />
				<ref bean="section2" />	
			</list>
		</property>
		
		<property name="sponsorships">
			<list>
				<ref bean="sponsorship3" />
				<ref bean="sponsorship2" />	
			</list>
		</property>
	</bean>
	
	<!-- Warranties -->
	

	<bean id="warranty1" class="domain.Warranty">
	
		<property name="title" value="El titulo de Warranty" />
		<property name="terms" value="Terminos, muchos terminos" />
		<property name="laws" value="Leyes,muchas leyes" />
		<property name="draft" value="Ejemplo de draft" />
		<property name="fixupTasks">
			<list>
				<ref bean="fixupTask1" />
				<ref bean="fixupTask2" />	
			</list>
		</property>
	</bean>
	
	<bean id="warranty2" class="domain.Warranty">
	
		<property name="title" value="El titulo de Warranty 2" />
		<property name="terms" value="Terminos, muchos terminos 2" />
		<property name="laws" value="Leyes,muchas leyes 2" />
		<property name="draft" value="Ejemplo de draft 2" />
		<property name="fixupTasks">
			<list>
				<ref bean="fixupTask1" />
				<ref bean="fixupTask2" />	
			</list>
		</property>
	</bean>
	
	<bean id="warranty3" class="domain.Warranty">
	
		<property name="title" value="El titulo de Warranty 3" />
		<property name="terms" value="Terminos, muchos terminos 3" />
		<property name="laws" value="Leyes,muchas leyes 3" />
		<property name="draft" value="Ejemplo de draft 3" />
		<property name="fixupTasks">
			<list>
				<ref bean="fixupTask1" />
				<ref bean="fixupTask2" />	
			</list>
		</property>
	</bean>
	
	
		<!-- WorkPlan -->
	

	<bean id="workPlan1" class="domain.WorkPlan">
	
		<property name="fixupTask" value="fixupTask1" />
		<property name="handyWoker" value="Elena Worker" />
		
		<property name="phases">
			<list>
				<ref bean="phase1" />
				<ref bean="phase2" />	
			</list>
		</property>
	</bean>
	
	<bean id="workPlan2" class="domain.WorkPlan">
	
		<property name="fixupTask" value="fixupTask2" />
		<property name="handyWoker" value="Pablo Worker" />
		<property name="phases">
			<list>
				<ref bean="phase1" />
				<ref bean="phase3" />	
			</list>
		</property>
	</bean>
	
	<bean id="workPlan3" class="domain.WorkPlan">
	
		<property name="fixupTask" value="fixupTask3" />
		<property name="handyWoker" value="Juan Worker" />
		<property name="phases">
			<list>
				<ref bean="phase3" />
				<ref bean="phase2" />	
			</list>
		</property>
	</bean>
	
	
	<!-------------------FixupTask-------------------------------->
	
	<bean id="fixupTask1" class="domain.FixupTask">
		<property name="moment" value="February 16, 2017 09:30"></property>
		<property name="description" value="Hay que arreglar la pata de la silla 4"></property>
		<property name="address" value="C/ Mani Manitas N3"></property>
		<property name="maximumPrice" value="15.00"></property>
		<property name="start" value="February 17, 2017 09:30"></property>
		<property name="end" value="February 18, 2017 09:30"></property>
		
		<property name="complaints">
			<list>
				<ref bean="complaint1" />
				<ref bean="complaint2" />
			</list>
		</property>
		<property name="customer" ref="customer1"> </property>
		<property name="category" ref="category1"> </property>
		<property name="warranty" ref="warranty1"> </property>
		<property name="applications">
			<list>
				<ref bean="application1" />
				<ref bean="application2" />
			</list>
		</property>
		<property name="workPlan" ref="workPlan1"> </property>

	</bean>
	
	
	<bean id="fixupTask2" class="domain.FixupTask">
		<property name="moment" value="October 11, 2017 09:30"></property>
		<property name="description" value="Bombilla rota"></property>
		<property name="address" value="C/ Croquetas de Jamón N3"></property>
		<property name="maximumPrice" value="14.00"></property>
		<property name="start" value="October 12, 2017 09:30"></property>
		<property name="end" value="October 18, 2017 09:30"></property>
		
		<property name="complaints">
			<list>
				<ref bean="complaint1" />
			</list>
		</property>
		<property name="customer" ref="customer2"> </property>
		<property name="category" ref="category2"> </property>
		<property name="warranty" ref="warranty2"> </property>
		<property name="applications">
			<list>
				<ref bean="application1" />
			</list>
		</property>
		<property name="workPlan" ref="workPlan2"> </property>

	</bean>
	
	<bean id="fixupTask3" class="domain.FixupTask">
		<property name="moment" value="June 11, 2017 09:30"></property>
		<property name="description" value="Hay que coserle el brazo a Woody"></property>
		<property name="address" value="C/ Toy Story N2"></property>
		<property name="maximumPrice" value="500.00"></property>
		<property name="start" value="June 12, 2017 09:30"></property>
		<property name="end" value="June 18, 2017 09:30"></property>
		
		<property name="complaints">
			<list>
			</list>
		</property>
		<property name="customer" ref="customer1"> </property>
		<property name="category" ref="category1"> </property>
		<property name="warranty" ref="warranty1"> </property>
		<property name="applications">
			<list>
	
			</list>
		</property>
		<property name="workPlan" ref="workPlan1"> </property>

	</bean>
	
	
	
	
	<!------------------------------- FOLDER ----------------------------------------------------->
		
		
		<!--folders del admin1-->
	
	<bean id="folder1Admin1">
		<property name="name" value="inBox" />
		<property name="system" value="true" />
		<property name="messages">
			<list/>
		</property>
		<property name="childFolder">
			<list/>
		</property>
	    <property name="parentFolder" ref="folder1Admin1" />
		<property name="actor" ref="administrator1" />
	</bean>
	
	
	<bean id="folder2Admin1">
		<property name="name" value="outBox" />
		<property name="system" value="true" />
		<property name="messages">
			<list/>
		</property>
		<property name="childFolder">
			<list/>
		</property>
	    <property name="parentFolder" ref="folder2Admin1" />
		<property name="actor" ref="administrator1" />
	</bean>
	
	
	<bean id="folder3Admin1">
		<property name="name" value="trashBox" />
		<property name="system" value="true" />
		<property name="messages">
			<list/>
		</property>
		<property name="childFolder">
			<list/>
		</property>
	    <property name="parentFolder" ref="folder3Admin1" />
		<property name="actor" ref="administrator1" />
	</bean>
	
	
	<bean id="folder4Admin1">
		<property name="name" value="spamBox" />
		<property name="system" value="true" />
		<property name="messages">
			<list/>
		</property>
		<property name="childFolder">
			<list/>
		</property>
	    <property name="parentFolder" ref="folder4Admin1" />
		<property name="actor" ref="administrator1" />
	</bean>
	
	
	
	<!--folders del admin2-->
	
	<bean id="folder1Admin2">
		<property name="name" value="inBox" />
		<property name="system" value="true" />
		<property name="messages">
			<list/>
		</property>
		<property name="childFolder">
			<list/>
		</property>
	    <property name="parentFolder" ref="folder1Admin2" />
		<property name="actor" ref="administrator2" />
	</bean>
	
	
	<bean id="folder2Admin2">
		<property name="name" value="outBox" />
		<property name="system" value="true" />
		<property name="messages">
			<list/>
		</property>
		<property name="childFolder">
			<list/>
		</property>
	    <property name="parentFolder" ref="folder2Admin2" />
		<property name="actor" ref="administrator2" />
	</bean>
	
	
	<bean id="folder3Admin2">
		<property name="name" value="trashBox" />
		<property name="system" value="true" />
		<property name="messages">
			<list/>
		</property>
		<property name="childFolder">
			<list/>
		</property>
	    <property name="parentFolder" ref="folder3Admin2" />
		<property name="actor" ref="administrator2" />
	</bean>
	
	
	<bean id="folder4Admin2">
		<property name="name" value="spamBox" />
		<property name="system" value="true" />
		<property name="messages">
			<list/>
		</property>
		<property name="childFolder">
			<list/>
		</property>
	    <property name="parentFolder" ref="folder4Admin2" />
		<property name="actor" ref="administrator2" />
	</bean>
	
	
	
	<!--folders del customer1 -->
	
	<bean id="folder1Customer1">
		<property name="name" value="inBox" />
		<property name="system" value="true" />
		<property name="messages">
			<list/>
		</property>
		<property name="childFolder">
			<list/>
		</property>
	    <property name="parentFolder" ref="folder1Customer1" />
		<property name="actor" ref="customer1" />
	</bean>
	
	<bean id="folder2Customer1">
		<property name="name" value="outBox" />
		<property name="system" value="true" />
		<property name="messages">
			<list/>
		</property>
		<property name="childFolder">
			<list/>
		</property>
	    <property name="parentFolder" ref="folder2Customer1" />
		<property name="actor" ref="customer1" />
	</bean>
	
	
	<bean id="folder3Customer1">
		<property name="name" value="trashBox" />
		<property name="system" value="true" />
		<property name="messages">
			<list/>
		</property>
		<property name="childFolder">
			<list/>
		</property>
	    <property name="parentFolder" ref="folder3Customer1" />
		<property name="actor" ref="customer1" />
	</bean>
	
	
	<bean id="folder4Customer1">
		<property name="name" value="spamBox" />
		<property name="system" value="true" />
		<property name="messages">
			<list/>
		</property>
		<property name="childFolder">
			<list/>
		</property>
	    <property name="parentFolder" ref="folder4Customer1" />
		<property name="actor" ref="customer1" />
	</bean>
	
	<!--folders del customer2 -->
	
	<bean id="folder1Customer2">
		<property name="name" value="inBox" />
		<property name="system" value="true" />
		<property name="messages">
			<list/>
		</property>
		<property name="childFolder">
			<list/>
		</property>
	    <property name="parentFolder" ref="folder1Customer2" />
		<property name="actor" ref="customer2" />
	</bean>
	
	<bean id="folder2Customer2">
		<property name="name" value="outBox" />
		<property name="system" value="true" />
		<property name="messages">
			<list/>
		</property>
		<property name="childFolder">
			<list/>
		</property>
	    <property name="parentFolder" ref="folder2Customer2" />
		<property name="actor" ref="customer2" />
	</bean>
	
	
	<bean id="folder3Customer2">
		<property name="name" value="trashBox" />
		<property name="system" value="true" />
		<property name="messages">
			<list/>
		</property>
		<property name="childFolder">
			<list/>
		</property>
	    <property name="parentFolder" ref="folder3Customer2" />
		<property name="actor" ref="customer2" />
	</bean>
	
	
	<bean id="folder4Customer2">
		<property name="name" value="spamBox" />
		<property name="system" value="true" />
		<property name="messages">
			<list/>
		</property>
		<property name="childFolder">
			<list/>
		</property>
	    <property name="parentFolder" ref="folder4Customer2" />
		<property name="actor" ref="customer2" />
	</bean>
	
	
	<!--folders del customer3 -->
	
	<bean id="folder1Customer3">
		<property name="name" value="inBox" />
		<property name="system" value="true" />
		<property name="messages">
			<list/>
		</property>
		<property name="childFolder">
			<list/>
		</property>
	    <property name="parentFolder" ref="folder1Customer3" />
		<property name="actor" ref="customer3" />
	</bean>
	
	<bean id="folder2Customer3">
		<property name="name" value="outBox" />
		<property name="system" value="true" />
		<property name="messages">
			<list/>
		</property>
		<property name="childFolder">
			<list/>
		</property>
	    <property name="parentFolder" ref="folder2Customer3" />
		<property name="actor" ref="customer3" />
	</bean>
	
	
	<bean id="folder3Customer3">
		<property name="name" value="trashBox" />
		<property name="system" value="true" />
		<property name="messages">
			<list/>
		</property>
		<property name="childFolder">
			<list/>
		</property>
	    <property name="parentFolder" ref="folder3Customer3" />
		<property name="actor" ref="customer3" />
	</bean>
	
	
	<bean id="folder4Customer3">
		<property name="name" value="spamBox" />
		<property name="system" value="true" />
		<property name="messages">
			<list/>
		</property>
		<property name="childFolder">
			<list/>
		</property>
	    <property name="parentFolder" ref="folder4Customer3" />
		<property name="actor" ref="customer3" />
	</bean>
	
	
	<!--folders del customer4 -->
	
	<bean id="folder1Customer4">
		<property name="name" value="inBox" />
		<property name="system" value="true" />
		<property name="messages">
			<list/>
		</property>
		<property name="childFolder">
			<list/>
		</property>
	    <property name="parentFolder" ref="folder1Customer4" />
		<property name="actor" ref="customer4" />
	</bean>
	
	<bean id="folder2Customer4">
		<property name="name" value="outBox" />
		<property name="system" value="true" />
		<property name="messages">
			<list/>
		</property>
		<property name="childFolder">
			<list/>
		</property>
	    <property name="parentFolder" ref="folder2Customer4" />
		<property name="actor" ref="customer4" />
	</bean>
	
	
	<bean id="folder3Customer4">
		<property name="name" value="trashBox" />
		<property name="system" value="true" />
		<property name="messages">
			<list/>
		</property>
		<property name="childFolder">
			<list/>
		</property>
	    <property name="parentFolder" ref="folder3Customer4" />
		<property name="actor" ref="customer4" />
	</bean>
	
	
	<bean id="folder4Customer4">
		<property name="name" value="spamBox" />
		<property name="system" value="true" />
		<property name="messages">
			<list/>
		</property>
		<property name="childFolder">
			<list/>
		</property>
	    <property name="parentFolder" ref="folder4Customer4" />
		<property name="actor" ref="customer4" />
	</bean>
	
	
	<!--folders del HandyWorker1 -->
	
	<bean id="folder1HandyWorker1">
		<property name="name" value="inBox" />
		<property name="system" value="true" />
		<property name="messages">
			<list/>
		</property>
		<property name="childFolder">
			<list/>
		</property>
	    <property name="parentFolder" ref="folder1HandyWorker1" />
		<property name="actor" ref="handyWorker1" />
	</bean>
	
	<bean id="folder2HandyWorker1">
		<property name="name" value="outBox" />
		<property name="system" value="true" />
		<property name="messages">
			<list/>
		</property>
		<property name="childFolder">
			<list/>
		</property>
	    <property name="parentFolder" ref="folder2HandyWorker1" />
		<property name="actor" ref="handyWorker1" />
	</bean>
	
	
	<bean id="folder3HandyWorker1">
		<property name="name" value="trashBox" />
		<property name="system" value="true" />
		<property name="messages">
			<list/>
		</property>
		<property name="childFolder">
			<list/>
		</property>
	    <property name="parentFolder" ref="folder3HandyWorker1" />
		<property name="actor" ref="handyWorker1" />
	</bean>
	
	
	<bean id="folder4HandyWorker1">
		<property name="name" value="spamBox" />
		<property name="system" value="true" />
		<property name="messages">
			<list/>
		</property>
		<property name="childFolder">
			<list/>
		</property>
	    <property name="parentFolder" ref="folder4HandyWorker1" />
		<property name="actor" ref="handyWorker1" />
	</bean>
	
	
	<!--folders del HandyWorker2 -->
	
	<bean id="folder1HandyWorker2">
		<property name="name" value="inBox" />
		<property name="system" value="true" />
		<property name="messages">
			<list/>
		</property>
		<property name="childFolder">
			<list/>
		</property>
	    <property name="parentFolder" ref="folder1HandyWorker2" />
		<property name="actor" ref="handyWorker2" />
	</bean>
	
	<bean id="folder2HandyWorker2">
		<property name="name" value="outBox" />
		<property name="system" value="true" />
		<property name="messages">
			<list/>
		</property>
		<property name="childFolder">
			<list/>
		</property>
	    <property name="parentFolder" ref="folder2HandyWorker2" />
		<property name="actor" ref="handyWorker2" />
	</bean>
	
	
	<bean id="folder3HandyWorker2">
		<property name="name" value="trashBox" />
		<property name="system" value="true" />
		<property name="messages">
			<list/>
		</property>
		<property name="childFolder">
			<list/>
		</property>
	    <property name="parentFolder" ref="folder3HandyWorker2" />
		<property name="actor" ref="handyWorker2" />
	</bean>
	
	
	<bean id="folder4HandyWorker2">
		<property name="name" value="spamBox" />
		<property name="system" value="true" />
		<property name="messages">
			<list/>
		</property>
		<property name="childFolder">
			<list/>
		</property>
	    <property name="parentFolder" ref="folder4HandyWorker2" />
		<property name="actor" ref="handyWorker2" />
	</bean>
	
	
	<!--folders del HandyWorker3 -->
	
	<bean id="folder1HandyWorker3">
		<property name="name" value="inBox" />
		<property name="system" value="true" />
		<property name="messages">
			<list/>
		</property>
		<property name="childFolder">
			<list/>
		</property>
	    <property name="parentFolder" ref="folder1HandyWorker3" />
		<property name="actor" ref="handyWorker3" />
	</bean>
	
	<bean id="folder2HandyWorker3">
		<property name="name" value="outBox" />
		<property name="system" value="true" />
		<property name="messages">
			<list/>
		</property>
		<property name="childFolder">
			<list/>
		</property>
	    <property name="parentFolder" ref="folder2HandyWorker3" />
		<property name="actor" ref="handyWorker3" />
	</bean>
	
	
	<bean id="folder3HandyWorker3">
		<property name="name" value="trashBox" />
		<property name="system" value="true" />
		<property name="messages">
			<list/>
		</property>
		<property name="childFolder">
			<list/>
		</property>
	    <property name="parentFolder" ref="folder3HandyWorker3" />
		<property name="actor" ref="handyWorker3" />
	</bean>
	
	
	<bean id="folder4HandyWorker3">
		<property name="name" value="spamBox" />
		<property name="system" value="true" />
		<property name="messages">
			<list/>
		</property>
		<property name="childFolder">
			<list/>
		</property>
	    <property name="parentFolder" ref="folder4HandyWorker3" />
		<property name="actor" ref="handyWorker3" />
	</bean>
	
	
	<!--folders del HandyWorker4 -->
	
	<bean id="folder1HandyWorker4">
		<property name="name" value="inBox" />
		<property name="system" value="true" />
		<property name="messages">
			<list/>
		</property>
		<property name="childFolder">
			<list/>
		</property>
	    <property name="parentFolder" ref="folder1HandyWorker4" />
		<property name="actor" ref="handyWorker4" />
	</bean>
	
	<bean id="folder2HandyWorker4">
		<property name="name" value="outBox" />
		<property name="system" value="true" />
		<property name="messages">
			<list/>
		</property>
		<property name="childFolder">
			<list/>
		</property>
	    <property name="parentFolder" ref="folder2HandyWorker4" />
		<property name="actor" ref="handyWorker4" />
	</bean>
	
	
	<bean id="folder3HandyWorker4">
		<property name="name" value="trashBox" />
		<property name="system" value="true" />
		<property name="messages">
			<list/>
		</property>
		<property name="childFolder">
			<list/>
		</property>
	    <property name="parentFolder" ref="folder3HandyWorker4" />
		<property name="actor" ref="handyWorker4" />
	</bean>
	
	
	<bean id="folder4HandyWorker4">
		<property name="name" value="spamBox" />
		<property name="system" value="true" />
		<property name="messages">
			<list/>
		</property>
		<property name="childFolder">
			<list/>
		</property>
	    <property name="parentFolder" ref="folder4HandyWorker4" />
		<property name="actor" ref="handyWorker4" />
	</bean>
	
	
	
	
	
	
	
	<!------------------------HANDYWORKER----------------------------------------------->
	
	
	<bean id="handyWorker1" class="domain.HandyWorker">
		<property name="name" value="Antonio"></property>
		<property name="middleName" value="Grinch"></property>
		<property name="surname" value="Papp"></property>
		<property name="photo"
			value="https://imgix.bustle.com/uploads/image/2017/12/20/a86b734f-aeaa-4310-8f73-5b2de4574930-37737f70-2a9c-4e5a-83dc-8e60232287f0-the-grinch.png?w=970&h=582&fit=crop&crop=faces&auto=format&q=70"></property>
		<property name="email" value="elgrinch@hotmail.com"></property>
		<property name="phone" value="652655856"></property>
		<property name="address" value="C/ Polo Norte"></property>
		<property name="banned" value="false"></property>
		<property name="suspicious" value="false"></property>
		
		
		<property name="userAccount" ref="userAccount7">
		</property>
		
		<property name="socialProfiles">
			<list>
				<ref bean="socialProfile1"></ref>
			</list>
		</property>

		<property name="folders">
			<list>
				<ref bean="folder1HandyWorker1" />
				<ref bean="folder2HandyWorker1" />
				<ref bean="folder3HandyWorker1" />
				<ref bean="folder4HandyWorker1" />
			</list>
		</property>
		<property name="messages">
			<list>
			</list>
		</property>
		
		<property name="make" value="Antonio Grinch Papp"></property>
		<property name="curriculum" value="curriculum1"></property>
		<property name="finder" value="finder1"></property>
		<property name="tutorials">
			<list>
				<ref bean="tutorial1" />
			</list>
		</property>
		<property name="applications">
			<list>
				<ref bean="application1" />
			</list>
		</property>
		<property name="workPlans">
			<list>
				<ref bean="workPlan1" />
			</list>
		</property>
		
		
		
		
		
		
		
		<bean id="handyWorker2" class="domain.HandyWorker">
		<property name="name" value="Luis"></property>
		<property name="middleName" value="Pokemaniako"></property>
		<property name="surname" value="Zumarraga"></property>
		<property name="photo"
			value="https://cdn.memegenerator.es/imagenes/memes/full/16/43/16433834.jpg"></property>
		<property name="email" value="pokeluisito@hotmail.com"></property>
		<property name="phone" value="652653567"></property>
		<property name="address" value="C/ Rataland"></property>
		<property name="banned" value="false"></property>
		<property name="suspicious" value="false"></property>
		
		
		<property name="userAccount" ref="userAccount8">
		</property>
		
		<property name="socialProfiles">
			<list>
				<ref bean="socialProfile2"></ref>
			</list>
		</property>

		<property name="folders">
			<list>
				<ref bean="folder1HandyWorker2" />
				<ref bean="folder2HandyWorker2" />
				<ref bean="folder3HandyWorker2" />
				<ref bean="folder4HandyWorker2" />
			</list>
		</property>
		<property name="messages">
			<list>
			</list>
		</property>
		
		<property name="make" value="Luis Pokemaniako Zumarraga"></property>
		<property name="curriculum" value="curriculum2"></property>
		<property name="finder" value="finder2"></property>
		<property name="tutorials">
			<list>
				<ref bean="tutorial2" />
			</list>
		</property>
		<property name="applications">
			<list>
				<ref bean="application2" />
			</list>
		</property>
		<property name="workPlans">
			<list>
				<ref bean="workPlan2" />
			</list>
		</property>

	</bean>
	
	
	
	
	<bean id="handyWorker3" class="domain.HandyWorker">
		<property name="name" value="Javi"></property>
		<property name="middleName" value="Rmano"></property>
		<property name="surname" value="Camunia"></property>
		<property name="photo"
			value="https://misanimales.com/wp-content/uploads/2018/05/curiosidades-del-perezoso.jpg"></property>
		<property name="email" value="camunon@hotmail.com"></property>
		<property name="phone" value="652343567"></property>
		<property name="address" value="C/ Lovaina"></property>
		<property name="banned" value="false"></property>
		<property name="suspicious" value="false"></property>
		
		
		<property name="userAccount" ref="userAccount9">
		</property>
		
		<property name="socialProfiles">
			<list>
				<ref bean="socialProfile3"></ref>
			</list>
		</property>

		<property name="folders">
			<list>
				<ref bean="folder1HandyWorker3" />
				<ref bean="folder2HandyWorker3" />
				<ref bean="folder3HandyWorker3" />
				<ref bean="folder4HandyWorker3" />
			</list>
		</property>
		<property name="messages">
			<list>
			</list>
		</property>
		
		<property name="make" value="Javi Rmano Camunia"></property>
		<property name="curriculum" value="curriculum3"></property>
		<property name="finder" value="finder3"></property>
		<property name="tutorials">
			<list>
				<ref bean="tutorial3" />
			</list>
		</property>
		<property name="applications">
			<list>
				<ref bean="application3" />
			</list>
		</property>
		<property name="workPlans">
			<list>
				<ref bean="workPlan3" />
			</list>
		</property>

	</bean>
	
	
	
	
	
	
	
	
	
	
	
	
	
	
	
	
	
	
	
	
	
	
	
	
	
	
	
</beans>
