<?xml version="1.0" encoding="UTF-8"?>

<!-- * PopulateDatabase.xml * * Copyright (C) 2018 Universidad de Sevilla 
	* * The use of this project is hereby constrained to the conditions of the 
	* TDG Licence, a copy of which you may download from * http://www.tdg-seville.info/License.html -->

<beans xmlns="http://www.springframework.org/schema/beans"
	xmlns:xsi="http://www.w3.org/2001/XMLSchema-instance"
	xsi:schemaLocation="
		http://www.springframework.org/schema/beans http://www.springframework.org/schema/beans/spring-beans.xsd
	">

	<!-- Date formats -->

	<bean id="completeDateFormat" class="java.text.SimpleDateFormat">
		<constructor-arg value="dd/MM/yyyy HH:mm:ss" />
	</bean>

	<!-- User accounts -->

	<bean id="userAccount1" class="security.UserAccount">
		<property name="username" value="admin1" />
		<property name="password" value="e00cf25ad42683b3df678c61f42c6bda" />
		<property name="banned" value="false" />
		<property name="authorities">
			<list>
				<bean class="security.Authority">
					<property name="authority" value="ADMIN" />
				</bean>
			</list>
		</property>
	</bean>
	
	<!-- La contraseña de system es intencional, no se puede acceder a esta cuenta -->
	
	<bean id="userAccountSystem" class="security.UserAccount">
		<property name="username" value="system" />
		<property name="password" value="system" />
		<property name="banned" value="false" />
		<property name="authorities">
			<list>
				<bean class="security.Authority">
					<property name="authority" value="ADMIN" />
				</bean>
			</list>
		</property>
	</bean>

	<bean id="userAccount15" class="security.UserAccount">
		<property name="username" value="admin2" />
		<property name="password" value="c84258e9c39059a89ab77d846ddab909" />
		<property name="banned" value="false" />
		<property name="authorities">
			<list>
				<bean class="security.Authority">
					<property name="authority" value="ADMIN" />
				</bean>
			</list>
		</property>
	</bean>

	<bean id="userAccount2" class="security.UserAccount">
		<property name="username" value="customer1" />
		<property name="password" value="ffbc4675f864e0e9aab8bdf7a0437010" />
		<property name="banned" value="false" />
		<property name="authorities">
			<list>
				<bean class="security.Authority">
					<property name="authority" value="CUSTOMER" />
				</bean>
			</list>
		</property>
	</bean>

	<bean id="userAccount4" class="security.UserAccount">
		<property name="username" value="customer2" />
		<property name="password" value="5ce4d191fd14ac85a1469fb8c29b7a7b" />
		<property name="banned" value="false" />
		<property name="authorities">
			<list>
				<bean class="security.Authority">
					<property name="authority" value="CUSTOMER" />
				</bean>
			</list>
		</property>
	</bean>

	<bean id="userAccount5" class="security.UserAccount">
		<property name="username" value="customer3" />
		<property name="password" value="033f7f6121501ae98285ad77f216d5e7" />
		<property name="banned" value="false" />
		<property name="authorities">
			<list>
				<bean class="security.Authority">
					<property name="authority" value="CUSTOMER" />
				</bean>
			</list>
		</property>
	</bean>

	<bean id="userAccount6" class="security.UserAccount">
		<property name="username" value="customer4" />
		<property name="password" value="55feb130be438e686ad6a80d12dd8f44" />
		<property name="banned" value="false" />
		<property name="authorities">
			<list>
				<bean class="security.Authority">
					<property name="authority" value="CUSTOMER" />
				</bean>
			</list>
		</property>
	</bean>


	<bean id="userAccount14" class="security.UserAccount">
		<property name="username" value="handyWorker1" />
		<property name="password" value="78da4cd657c85d3cf54ae4497ed223f2" />
		<property name="banned" value="false" />
		<property name="authorities">
			<list>
				<bean class="security.Authority">
					<property name="authority" value="HANDYWORKER" />
				</bean>
			</list>
		</property>
	</bean>


	<bean id="userAccount8" class="security.UserAccount">
		<property name="username" value="handyWorker2" />
		<property name="password" value="118ad5acc8ff3ea8006c280b310cd492" />
		<property name="banned" value="false" />
		<property name="authorities">
			<list>
				<bean class="security.Authority">
					<property name="authority" value="HANDYWORKER" />
				</bean>
			</list>
		</property>
	</bean>


	<bean id="userAccount9" class="security.UserAccount">
		<property name="username" value="handyWorker3" />
		<property name="password" value="c210fdd660ad5034b88ad8bb9c135c26" />
		<property name="banned" value="false" />
		<property name="authorities">
			<list>
				<bean class="security.Authority">
					<property name="authority" value="HANDYWORKER" />
				</bean>
			</list>
		</property>
	</bean>


	<bean id="userAccount10" class="security.UserAccount">
		<property name="username" value="handyWorker4" />
		<property name="password" value="e14d43d31080bd377e4984615da9f3aa" />
		<property name="banned" value="false" />
		<property name="authorities">
			<list>
				<bean class="security.Authority">
					<property name="authority" value="HANDYWORKER" />
				</bean>
			</list>
		</property>
	</bean>

	<!-- Other domain beans come here -->

	<!-- Administrators -->

	<bean id="administrator1" class="domain.Administrator">
		<property name="name" value="Mario" />
		<property name="middleName" value="Xavier" />
		<property name="surname" value="García" />
		<property name="photo"
			value="https://cdn.pixabay.com/photo/2017/06/26/02/47/people-2442565_960_720.jpg" />
		<property name="email" value="maxagar@gmail.com" />
		<property name="phone" value="+34(456)123456789" />
		<property name="address" value="C/Calle, 32" />
		<property name="suspicious" value="true" />
		<property name="userAccount" ref="userAccount1" />
	</bean>
	
	<bean id="system" class="domain.Administrator">
		<property name="name" value="System" />
		<property name="middleName" value="System" />
		<property name="surname" value="System" />
		<property name="email" value="system@system.sys" />
		<property name="address" value="C/System, 32" />
		<property name="suspicious" value="false" />
		<property name="userAccount" ref="userAccountSystem" />
	</bean>

	<bean id="administrator2" class="domain.Administrator">
		<property name="name" value="Clara" />
		<property name="surname" value="Prats" />
		<property name="email" value="maxagar@gmail.com" />
		<property name="phone" value="+34(456)123456759" />
		<property name="suspicious" value="false" />
		<property name="userAccount" ref="userAccount15" />
	</bean>

	<!-- Application -->

	<bean id="application1" class="domain.Application">
		<property name="price" value="3.14" />
		<property name="moment">
			<bean id="momentApplication1" factory-bean="completeDateFormat"
				factory-method="parse">
				<constructor-arg value="28/10/2017 23:59:59" />
			</bean>
		</property>
		<property name="creditCard">
			<bean name="creditCardApplication4" class="domain.CreditCard">
				<property name="holderName" value="Paco Pepe Pérez" />
				<property name="brandName" value="VISA" />
				<property name="number" value="4556042640541332" />
				<property name="expirationDate">
					<bean id="expirationDateCreditCard2" factory-bean="completeDateFormat"
						factory-method="parse">
						<constructor-arg value="28/10/2020 23:59:59" />
					</bean>
				</property>
				<property name="cvvCode" value="452" />
			</bean>
		</property>
		<property name="status" value="ACCEPTED" />
		<property name="workerComments" value="I work hard" />
		<property name="handyWorker" ref="handyWorker1" />
		<property name="fixupTask" ref="fixupTask1" />
	</bean>
	
	<bean id="application6" class="domain.Application">
		<property name="price" value="3.14" />
		<property name="moment">
			<bean id="momentApplication1" factory-bean="completeDateFormat"
				factory-method="parse">
				<constructor-arg value="28/10/2017 23:59:59" />
			</bean>
		</property>
		<property name="status" value="REJECTED" />
		<property name="workerComments" value="I work hard" />
		<property name="handyWorker" ref="handyWorker1" />
		<property name="fixupTask" ref="fixupTask2" />
	</bean>
	
	<bean id="application7" class="domain.Application">
		<property name="price" value="3.14" />
		<property name="moment">
			<bean id="momentApplication1" factory-bean="completeDateFormat"
				factory-method="parse">
				<constructor-arg value="28/10/2017 23:59:59" />
			</bean>
		</property>
		<property name="status" value="PENDING" />
		<property name="workerComments" value="I work hard" />
		<property name="handyWorker" ref="handyWorker1" />
		<property name="fixupTask" ref="fixupTask3" />
	</bean>

	<bean id="application2" class="domain.Application">
		<property name="price" value="12.34" />
		<property name="moment">
			<bean id="momentApplication2" factory-bean="completeDateFormat"
				factory-method="parse">
				<constructor-arg value="31/10/2018 00:00:00" />
			</bean>
		</property>
		<property name="status" value="PENDING" />
		<property name="workerComments" value="I work very hard" />
		<property name="customerComments" value="OK" />
		<property name="creditCard">
			<bean name="creditCardApplication2" class="domain.CreditCard">
				<property name="holderName" value="Paco Pepe Pérez" />
				<property name="brandName" value="VISA" />
				<property name="number" value="4556042640541332" />
				<property name="expirationDate">
					<bean id="expirationDateCreditCard2" factory-bean="completeDateFormat"
						factory-method="parse">
						<constructor-arg value="28/10/2020 23:59:59" />
					</bean>
				</property>
				<property name="cvvCode" value="452" />
			</bean>
		</property>
		<property name="handyWorker" ref="handyWorker2" />
		<property name="fixupTask" ref="fixupTask2" />
	</bean>

	<bean id="application3" class="domain.Application">
		<property name="price" value="10.43" />
		<property name="moment">
			<bean id="momentApplication3" factory-bean="completeDateFormat"
				factory-method="parse">
				<constructor-arg value="12/10/2017 00:00:00" />
			</bean>
		</property>
		<property name="creditCard">
			<bean name="creditCardApplication5" class="domain.CreditCard">
				<property name="holderName" value="Paco Pepe Pérez" />
				<property name="brandName" value="VISA" />
				<property name="number" value="4556042640541332" />
				<property name="expirationDate">
					<bean id="expirationDateCreditCard2" factory-bean="completeDateFormat"
						factory-method="parse">
						<constructor-arg value="28/10/2020 23:59:59" />
					</bean>
				</property>
				<property name="cvvCode" value="452" />
			</bean>
		</property>
		<property name="status" value="ACCEPTED" />
		<property name="handyWorker" ref="handyWorker3" />
		<property name="fixupTask" ref="fixupTask3" />
	</bean>
	
	
	<bean id="application4" class="domain.Application">
		<property name="price" value="11.34" />
		<property name="moment">
			<bean id="momentApplication4" factory-bean="completeDateFormat"
				factory-method="parse">
				<constructor-arg value="31/10/2018 00:00:00" />
			</bean>
		</property>
		<property name="status" value="ACCEPTED" />
		<property name="workerComments" value="I work very hard" />
		<property name="customerComments" value="OK" />
		<property name="creditCard">
			<bean name="creditCardApplication4" class="domain.CreditCard">
				<property name="holderName" value="Paco Pepe Pérez" />
				<property name="brandName" value="VISA" />
				<property name="number" value="4556042640541332" />
				<property name="expirationDate">
					<bean id="expirationDateCreditCard4" factory-bean="completeDateFormat"
						factory-method="parse">
						<constructor-arg value="28/10/2020 23:59:59" />
					</bean>
				</property>
				<property name="cvvCode" value="452" />
			</bean>
		</property>
		<property name="handyWorker" ref="handyWorker4" />
		<property name="fixupTask" ref="fixupTask2" />
	</bean>
	
	<bean id="application5" class="domain.Application">
		<property name="price" value="1.00" />
		<property name="moment">
			<bean id="momentApplication4" factory-bean="completeDateFormat"
				factory-method="parse">
				<constructor-arg value="31/10/2018 00:00:00" />
			</bean>
		</property>
		<property name="status" value="ACCEPTED" />
		<property name="workerComments" value="I work very hard" />
		<property name="customerComments" value="OK" />
		<property name="creditCard">
			<bean name="creditCardApplication4" class="domain.CreditCard">
				<property name="holderName" value="Paco Pepe Pérez" />
				<property name="brandName" value="VISA" />
				<property name="number" value="4556042640541332" />
				<property name="expirationDate">
					<bean id="expirationDateCreditCard4" factory-bean="completeDateFormat"
						factory-method="parse">
						<constructor-arg value="28/10/2020 23:59:59" />
					</bean>
				</property>
				<property name="cvvCode" value="452" />
			</bean>
		</property>
		<property name="handyWorker" ref="handyWorker1" />
		<property name="fixupTask" ref="fixupTask4" />
	</bean>

	<!-- Categories -->

	<bean id="categoryRoot" class="domain.Category">
		<property name="nameEnglish" value="CATEGORY" />
		<property name="nameSpanish" value="CATEGORÍA" />
		<property name="parentCategory" ref="categoryRoot" />
	</bean>

	<bean id="categoryCarpentry" class="domain.Category">
		<property name="nameEnglish" value="Carpentry" />
		<property name="nameSpanish" value="Carpintería" />
		<property name="parentCategory" ref="categoryRoot" />
	</bean>

	<bean id="categoryCeilingRepair" class="domain.Category">
		<property name="nameEnglish" value="CeilingRepair" />
		<property name="nameSpanish" value="Reparación de techos" />
		<property name="parentCategory" ref="categoryConcreteWork" />
	</bean>

	<bean id="categoryCleaning" class="domain.Category">
		<property name="nameEnglish" value="Cleaning" />
		<property name="nameSpanish" value="Limpieza" />
		<property name="parentCategory" ref="categoryRoot" />
	</bean>

	<bean id="categoryConcreteWork" class="domain.Category">
		<property name="nameEnglish" value="ConcreteWork" />
		<property name="nameSpanish" value="Trabajos con hormigón" />
		<property name="parentCategory" ref="categoryRoot" />
	</bean>

	<bean id="categoryDoors" class="domain.Category">
		<property name="nameEnglish" value="Doors" />
		<property name="nameSpanish" value="Puertas" />
		<property name="parentCategory" ref="categoryCarpentry" />
	</bean>

	<bean id="categoryElectricalWiring" class="domain.Category">
		<property name="nameEnglish" value="ElectricalWiring" />
		<property name="nameSpanish" value="Cableado Eléctrico" />
		<property name="parentCategory" ref="categoryRoot" />
	</bean>

	<bean id="categoryFanInstallation" class="domain.Category">
		<property name="nameEnglish" value="FanInstallation" />
		<property name="nameSpanish" value="Instalación de ventiladores" />
		<property name="parentCategory" ref="categoryElectricalWiring" />
	</bean>

	<bean id="categoryFenceFixing" class="domain.Category">
		<property name="nameEnglish" value="FenceFixing" />
		<property name="nameSpanish" value="Reparación de vallas" />
		<property name="parentCategory" ref="categoryHomeSecuritySystems" />
	</bean>

	<bean id="categoryHomeSecuritySystems" class="domain.Category">
		<property name="nameEnglish" value="HomeSecuritySystems" />
		<property name="nameSpanish" value="Sistemas de seguridad para el hogar" />
		<property name="parentCategory" ref="categoryRoot" />
	</bean>

	<bean id="categoryInsulationInstallation" class="domain.Category">
		<property name="nameEnglish" value="InsulationInstallation" />
		<property name="nameSpanish" value="Instalación de aislamiento" />
		<property name="parentCategory" ref="categoryRoot" />
	</bean>

	<bean id="categoryLampRepairs" class="domain.Category">
		<property name="nameEnglish" value="LampRepairs" />
		<property name="nameSpanish" value="Reparación de lámparas" />
		<property name="parentCategory" ref="categoryElectricalWiring" />
	</bean>

	<bean id="categoryMoving" class="domain.Category">
		<property name="nameEnglish" value="Moving" />
		<property name="nameSpanish" value="Mudanzas" />
		<property name="parentCategory" ref="categoryRoot" />
	</bean>

	<bean id="categoryPainting" class="domain.Category">
		<property name="nameEnglish" value="Painting" />
		<property name="nameSpanish" value="Pintado" />
		<property name="parentCategory" ref="categoryRoot" />
	</bean>

	<bean id="categoryPestControl" class="domain.Category">
		<property name="nameEnglish" value="PestControl" />
		<property name="nameSpanish" value="Control de plagas" />
		<property name="parentCategory" ref="categoryCleaning" />
	</bean>

	<bean id="categoryPlumbingRepairs" class="domain.Category">
		<property name="nameEnglish" value="PlumbingRepairs" />
		<property name="nameSpanish" value="Reparación de tuberías" />
		<property name="parentCategory" ref="categoryRoot" />
	</bean>

	<bean id="categoryRoofing" class="domain.Category">
		<property name="nameEnglish" value="Roofing" />
		<property name="nameSpanish" value="Techado" />
		<property name="parentCategory" ref="categoryConcreteWork" />
	</bean>

	<bean id="categoryShelfInstallation" class="domain.Category">
		<property name="nameEnglish" value="ShelfInstallation" />
		<property name="nameSpanish" value="Instalación de estanterías" />
		<property name="parentCategory" ref="categoryCarpentry" />
	</bean>

	<bean id="categorySolarPanels" class="domain.Category">
		<property name="nameEnglish" value="SolarPanels" />
		<property name="nameSpanish" value="Paneles Solares" />
		<property name="parentCategory" ref="categoryElectricalWiring" />
	</bean>

	<bean id="categorySoundProofing" class="domain.Category">
		<property name="nameEnglish" value="SoundProofing" />
		<property name="nameSpanish" value="Amortiguación de sonido" />
		<property name="parentCategory" ref="categoryInsulationInstallation" />
	</bean>

	<bean id="categorySprinklerRepair" class="domain.Category">
		<property name="nameEnglish" value="SprinklerRepair" />
		<property name="nameSpanish" value="Reparación de aspersores" />
		<property name="parentCategory" ref="categoryElectricalWiring" />
	</bean>

	<bean id="categoryWindowRepair" class="domain.Category">
		<property name="nameEnglish" value="WindowRepair" />
		<property name="nameSpanish" value="Reparación de ventanas" />
		<property name="parentCategory" ref="categoryCarpentry" />
	</bean>
	
	<!-- ___________________Customers___________________________________ -->
	<bean id="customer1" class="domain.Customer">
		<property name="name" value="Alfonso"></property>
		<property name="middleName" value="HackerMan"></property>
		<property name="surname" value="Alarcon"></property>
		<property name="photo"
			value="https://cdn.pixabay.com/user/2015/01/20/20-56-42-330_250x250.jpg"></property>
		<property name="email" value="uncorreonormal@hotmail.com"></property>
		<property name="phone" value="+34(456)123456718"></property>
		<property name="address" value="C/ sal y arena"></property>
		<property name="suspicious" value="false"></property>
		<property name="score" value="0.75"></property>
		<property name="userAccount" ref="userAccount2"></property>
		<property name="fixupTasks">
			<list>
				<ref bean="fixupTask1" />
				<ref bean="fixupTask5" />
			</list>
		</property> 
	</bean>

	<bean id="customer2" class="domain.Customer">
		<property name="name" value="Pablo"></property>
		<property name="middleName" value="HackerBoy"></property>
		<property name="surname" value="Pino"></property>
		<property name="photo"
			value="https://cdn.pixabay.com/user/2015/01/20/20-56-42-330_250x250.jpg"></property>
		<property name="email" value="uncorreomaslargo@hotmail.com"></property>
		<property name="phone" value="+34(456)123456717"></property>
		<property name="address" value="C/ esperanza de rafael"></property>
		<property name="suspicious" value="false"></property>
		<property name="score" value="0.75"></property>
		<property name="userAccount" ref="userAccount4">
		</property>
		<property name="fixupTasks">
			<list>
				<ref bean="fixupTask2" />
			</list>
		</property> 
	</bean>

	<bean id="customer3" class="domain.Customer">
		<property name="name" value="Juan"></property>
		<property name="middleName" value=""></property>
		<property name="surname" value="De la Aceituna"></property>
		<property name="photo"
			value="https://cdn.pixabay.com/user/2015/01/20/20-56-42-330_250x250.jpg"></property>
		<property name="email" value="juandelaaceitunaynooliva@hotmail.com"></property>
		<property name="phone" value="+34(456)123456716"></property>
		<property name="address" value="C/ Perdida de la mano de Dios"></property>
		<property name="suspicious" value="false"></property>
		<property name="score" value="0.81"></property>
		<property name="userAccount" ref="userAccount5"></property>
		<property name="fixupTasks">
			<list>
				<ref bean="fixupTask3" />
			</list>
		</property> 
	</bean>

	<bean id="customer4" class="domain.Customer">
		<property name="name" value="Elena"></property>
		<property name="middleName" value="TomasLena"></property>
		<property name="surname" value="Molina"></property>
		<property name="photo"
			value="https://cdn.pixabay.com/user/2015/01/20/20-56-42-330_250x250.jpg"></property>
		<property name="email" value="tomaslena@hotmail.com"></property>
		<property name="phone" value="+34(456)123456715"></property>
		<property name="address" value="C/ pasada la estacion del ave"></property>
		<property name="suspicious" value="false"></property>
		<property name="score" value="0.65"></property>
		<property name="userAccount" ref="userAccount6"></property>
		<property name="fixupTasks">
			<list>
				<ref bean="fixupTask4" />
			</list>
		</property> 
	</bean>

	<!-- Phase -->

	<bean id="phase1" class="domain.Phase">

		<property name="title" value="phase1" />
		<property name="description" value="Coger el telefono antes de hacer nada" />
		<property name="start" value="February 17, 2017 09:30"></property>
		<property name="end" value="February 18, 2017 09:30"></property>
		<property name="workPlan" ref="workPlan1"></property>
	</bean>
	
	<bean id="phase4" class="domain.Phase">
		<property name="title" value="phase4" />
		<property name="description" value="Coger el telefono antes de hacer nada" />
		<property name="start" value="February 17, 2017 09:30"></property>
		<property name="end" value="February 18, 2017 09:30"></property>
		<property name="workPlan" ref="workPlan1"></property>
	</bean>

	<bean id="phase2" class="domain.Phase">
		<property name="title" value="phase2" />
		<property name="description" value="Coger el telefono antes de hacer nada" />
		<property name="start" value="February 16, 2017 09:30"></property>
		<property name="end" value="February 18, 2017 09:30"></property>
		<property name="workPlan" ref="workPlan2"></property>
	</bean>

	<bean id="phase3" class="domain.Phase">
		<property name="title" value="phase3" />
		<property name="description" value="Coger el telefono antes de hacer nada" />
		<property name="start" value="February 15, 2017 09:30"></property>
		<property name="end" value="February 18, 2017 09:30"></property>
		<property name="workPlan" ref="workPlan3"></property>
	</bean>
	
	<bean id="phase5" class="domain.Phase">
		<property name="title" value="phase5" />
		<property name="description" value="Coger el telefono antes de hacer algo" />
		<property name="start" value="February 15, 2017 09:30"></property>
		<property name="end" value="February 18, 2017 09:30"></property>
		<property name="workPlan" ref="workPlan4"></property>
	</bean>
	
	

	<!-- WorkPlan -->


	<bean id="workPlan1" class="domain.WorkPlan">
		<property name="fixupTask" ref="fixupTask1" />
		<property name="handyWorker" ref="handyWorker1" />
		<property name="phases">
			<list>
				<ref bean="phase1" />
				<ref bean="phase4" />
			</list>
		</property>
	</bean>

	<bean id="workPlan2" class="domain.WorkPlan">
		<property name="fixupTask" ref="fixupTask2" />
		<property name="handyWorker" ref="handyWorker2" />
		<property name="phases">
			<list>
				<ref bean="phase2" />
			</list>
		</property>
	</bean>

	<bean id="workPlan3" class="domain.WorkPlan">
		<property name="fixupTask" ref="fixupTask3" />
		<property name="handyWorker" ref="handyWorker3" />
		<property name="phases">
			<list>
				<ref bean="phase3" />
			</list>
		</property>
	</bean>
	
	
	
	<bean id="workPlan4" class="domain.WorkPlan">
		<property name="fixupTask" ref="fixupTask4" />
		<property name="handyWorker" ref="handyWorker4" />
		<property name="phases">
			<list>
				<ref bean="phase5" />
			</list>
		</property>
	</bean>

	<!--____________ FixupTask_________________________________ -->

	<bean id="fixupTask1" class="domain.FixupTask">
		<property name="moment" value="February 16, 2017 09:30"></property>
		<property name="description" value="Hay que arreglar la pata de la silla 4"></property>
		<property name="address" value="C/ Mani Manitas N3"></property>
		<property name="maximumPrice" value="15.00"></property>
		<property name="start" value="February 17, 2017 09:30"></property>
		<property name="end" value="February 18, 2017 09:30"></property>
		<property name="ticker" value="181103-RTIB01" />
		<property name="customer" ref="customer1"></property>
		<property name="category" ref="categoryCarpentry"></property>
		<property name="warranty" ref="warranty1" />
		<property name="applications">
			<list>
				<ref bean="application1" />
			</list>
		</property>
		<property name="complaints">
			<list>
			</list>
		</property>
	</bean>

	<bean id="fixupTask6" class="domain.FixupTask">
		<property name="moment" value="February 16, 2017 09:30"></property>
		<property name="description" value="Hay que arreglar la pata de la silla 5"></property>
		<property name="address" value="C/ Mani Manitas N3"></property>
		<property name="maximumPrice" value="132424.12"></property>
		<property name="start" value="February 17, 2018 09:30"></property>
		<property name="end" value="February 18, 2019 09:30"></property>
		<property name="ticker" value="181103-RTIB56" />
		<property name="customer" ref="customer1"></property>
		<property name="category" ref="categoryCarpentry"></property>
		<property name="warranty" ref="warranty1" />
		<property name="applications">
			<list />
		</property>
		<property name="complaints">
			<list />
		</property>
	</bean>

	<bean id="fixupTask2" class="domain.FixupTask">
		<property name="moment" value="October 11, 2017 09:30"></property>
		<property name="description" value="Bombilla rota"></property>
		<property name="address" value="C/ Croquetas de Jamón N3"></property>
		<property name="maximumPrice" value="14.00"></property>
		<property name="start" value="October 12, 2017 09:30"></property>
		<property name="end" value="October 18, 2017 09:30"></property>
		<property name="ticker" value="181103-RTIB02" />
		<property name="customer" ref="customer2"></property>
		<property name="category" ref="categoryCleaning"></property>
		<property name="warranty" ref="warranty2" />
		<property name="applications">
			<list>
				<ref bean="application2" />
				<ref bean="application4" />
				<ref bean="application6" />
			</list>
		</property>
		<property name="complaints">
			<list>
			</list>
		</property>
	</bean>

	<bean id="fixupTask3" class="domain.FixupTask">
		<property name="moment" value="June 11, 2017 09:30"></property>
		<property name="description" value="Hay que coserle el brazo a Woody"></property>
		<property name="address" value="C/ Toy Story N2"></property>
		<property name="maximumPrice" value="50.00"></property>
		<property name="start" value="June 12, 2017 09:30"></property>
		<property name="end" value="June 18, 2017 09:30"></property>
		<property name="ticker" value="181103-RTIB03" />
		<property name="customer" ref="customer3"></property>
		<property name="category" ref="categoryCarpentry"></property>
		<property name="warranty" ref="warranty3" />
		<property name="applications">
			<list>
				<ref bean="application3" />
				<ref bean="application7" />
			</list>
		</property>
		<property name="complaints">
			<list>
			</list>
		</property>
	</bean>
	
	<bean id="fixupTask4" class="domain.FixupTask">
		<property name="moment" value="June 11, 2017 09:30"></property>
		<property name="description" value="Tejer cosas"></property>
		<property name="address" value="C/ Toy Story N2"></property>
		<property name="maximumPrice" value="50.00"></property>
		<property name="start" value="June 12, 2017 09:30"></property>
		<property name="end" value="June 18, 2017 09:30"></property>
		<property name="ticker" value="181103-RTIBA3" />
		<property name="customer" ref="customer4"></property>
		<property name="category" ref="categoryCarpentry"></property>
		<property name="warranty" ref="warranty3" />
		<property name="applications">
			<list>
				<ref bean="application5" />
			</list>
		</property>
		<property name="complaints">
			<list>
			</list>
		</property>
	</bean>
	
	<bean id="fixupTask5" class="domain.FixupTask">
		<property name="moment" value="June 11, 2017 09:30"></property>
		<property name="description" value="Tarea para queries"></property>
		<property name="address" value="C/ Toy Story N2"></property>
		<property name="maximumPrice" value="50.00"></property>
		<property name="start" value="June 12, 2017 09:30"></property>
		<property name="end" value="June 18, 2017 09:30"></property>
		<property name="ticker" value="181103-RTEAS3" />
		<property name="customer" ref="customer1"></property>
		<property name="category" ref="categoryCarpentry"></property>
		<property name="warranty" ref="warranty3" />
		<property name="applications">
			<list>
			</list>
		</property>
		<property name="complaints">
			<list>
			</list>
		</property>
	</bean>


	<!-- Warranties -->


	<bean id="warranty1" class="domain.Warranty">
		<property name="title" value="El titulo de Warranty" />
		<property name="terms" value="Terminos, muchos terminos" />
		<property name="laws" value="Leyes,muchas leyes" />
		<property name="draft" value="true" />
	</bean>

	<bean id="warranty2" class="domain.Warranty">
		<property name="title" value="El titulo de Warranty 2" />
		<property name="terms" value="Terminos, muchos terminos 2" />
		<property name="laws" value="Leyes,muchas leyes 2" />
		<property name="draft" value="false" />
	</bean>

	<bean id="warranty3" class="domain.Warranty">
		<property name="title" value="El titulo de Warranty 3" />
		<property name="terms" value="Terminos, muchos terminos 3" />
		<property name="laws" value="Leyes,muchas leyes 3" />
		<property name="draft" value="false" />
	</bean>
	
	<bean id="warranty4" class="domain.Warranty">
		<property name="title" value="El titulo de Warranty 4" />
		<property name="terms" value="Terminos, muchos terminos 4" />
		<property name="laws" value="Leyes,muchas leyes 4" />
		<property name="draft" value="true" />
	</bean>
	
	<bean id="warranty5" class="domain.Warranty">
		<property name="title" value="La Constitución Española" />
		<property name="terms" value="Algo de España y los españoles" />
		<property name="laws" value="Las hicieron en el 78" />
		<property name="draft" value="false" />
	</bean>
	
	<bean id="warranty6" class="domain.Warranty">
		<property name="title" value="La selección natural" />
		<property name="terms" value="Los seres evolucionan" />
		<property name="laws" value="La del mejor adaptado" />
		<property name="draft" value="true" />
	</bean>

	<!-- __________________________________ FOLDER _________________________________ -->

	<!-- Folders del sistema -->
	
	<!--folders del customer1 -->

	<bean id="inboxSystem" class="domain.Folder">
		<property name="name" value="inBox" />
		<property name="system" value="true" />
		<property name="parentFolder" ref="inboxSystem" />
		<property name="actor" ref="system" />
	</bean>

	<bean id="outboxSystem" class="domain.Folder">
		<property name="name" value="outBox" />
		<property name="system" value="true" />
		<property name="parentFolder" ref="outboxSystem" />
		<property name="actor" ref="system" />
	</bean>


	<bean id="trashboxSystem" class="domain.Folder">
		<property name="name" value="trashBox" />
		<property name="system" value="true" />
		<property name="parentFolder" ref="trashboxSystem" />
		<property name="actor" ref="system" />
	</bean>


	<bean id="spamboxSystem" class="domain.Folder">
		<property name="name" value="spamBox" />
		<property name="system" value="true" />
		<property name="parentFolder" ref="spamboxSystem" />
		<property name="actor" ref="system" />
	</bean>

	<!--folders del customer1 -->

	<bean id="folder1Customer1" class="domain.Folder">
		<property name="name" value="inBox" />
		<property name="system" value="true" />
		<property name="parentFolder" ref="folder1Customer1" />
		<property name="actor" ref="customer1" />
	</bean>

	<bean id="folder2Customer1" class="domain.Folder">
		<property name="name" value="outBox" />
		<property name="system" value="true" />
		<property name="parentFolder" ref="folder2Customer1" />
		<property name="actor" ref="customer1" />
	</bean>


	<bean id="folder3Customer1" class="domain.Folder">
		<property name="name" value="trashBox" />
		<property name="system" value="true" />
		<property name="parentFolder" ref="folder3Customer1" />
		<property name="actor" ref="customer1" />
	</bean>


	<bean id="folder4Customer1" class="domain.Folder">
		<property name="name" value="spamBox" />
		<property name="system" value="true" />
		<property name="parentFolder" ref="folder4Customer1" />
		<property name="actor" ref="customer1" />
	</bean>

<bean id="folder5Customer1" class="domain.Folder">
		<property name="name" value="testbox" />
		<property name="system" value="false" />
		<property name="parentFolder" ref="folder5Customer1" />
		<property name="actor" ref="customer1" />
	</bean>
	<!--folders del customer2 -->

	<bean id="folder1Customer2" class="domain.Folder">
		<property name="name" value="inBox" />
		<property name="system" value="true" />
		<property name="parentFolder" ref="folder1Customer2" />
		<property name="actor" ref="customer2" />
	</bean>

	<bean id="folder2Customer2" class="domain.Folder">
		<property name="name" value="outBox" />
		<property name="system" value="true" />
		<property name="parentFolder" ref="folder2Customer2" />
		<property name="actor" ref="customer2" />
	</bean>


	<bean id="folder3Customer2" class="domain.Folder">
		<property name="name" value="trashBox" />
		<property name="system" value="true" />
		<property name="parentFolder" ref="folder3Customer2" />
		<property name="actor" ref="customer2" />
	</bean>


	<bean id="folder4Customer2" class="domain.Folder">
		<property name="name" value="spamBox" />
		<property name="system" value="true" />
		<property name="parentFolder" ref="folder4Customer2" />
		<property name="actor" ref="customer2" />
	</bean>


	<!--folders del customer3 -->

	<bean id="folder1Customer3" class="domain.Folder">
		<property name="name" value="inBox" />
		<property name="system" value="true" />
		<property name="parentFolder" ref="folder1Customer3" />
		<property name="actor" ref="customer3" />
	</bean>

	<bean id="folder2Customer3" class="domain.Folder">
		<property name="name" value="outBox" />
		<property name="system" value="true" />
		<property name="parentFolder" ref="folder2Customer3" />
		<property name="actor" ref="customer3" />
	</bean>


	<bean id="folder3Customer3" class="domain.Folder">
		<property name="name" value="trashBox" />
		<property name="system" value="true" />
		<property name="parentFolder" ref="folder3Customer3" />
		<property name="actor" ref="customer3" />
	</bean>


	<bean id="folder4Customer3" class="domain.Folder">
		<property name="name" value="spamBox" />
		<property name="system" value="true" />
		<property name="parentFolder" ref="folder4Customer3" />
		<property name="actor" ref="customer3" />
	</bean>


	<!--folders del customer4 -->

	<bean id="folder1Customer4" class="domain.Folder">
		<property name="name" value="inBox" />
		<property name="system" value="true" />
		<property name="parentFolder" ref="folder1Customer4" />
		<property name="actor" ref="customer4" />
	</bean>

	<bean id="folder2Customer4" class="domain.Folder">
		<property name="name" value="outBox" />
		<property name="system" value="true" />
		<property name="parentFolder" ref="folder2Customer4" />
		<property name="actor" ref="customer4" />
	</bean>


	<bean id="folder3Customer4" class="domain.Folder">
		<property name="name" value="trashBox" />
		<property name="system" value="true" />
		<property name="parentFolder" ref="folder3Customer4" />
		<property name="actor" ref="customer4" />
	</bean>


	<bean id="folder4Customer4" class="domain.Folder">
		<property name="name" value="spamBox" />
		<property name="system" value="true" />
		<property name="parentFolder" ref="folder4Customer4" />
		<property name="actor" ref="customer4" />
	</bean>


	<!--folders del HandyWorker1 -->

	<bean id="folder1HandyWorker1" class="domain.Folder">
		<property name="name" value="inBox" />
		<property name="system" value="true" />
		<property name="parentFolder" ref="folder1HandyWorker1" />
		<property name="actor" ref="handyWorker1" />
	</bean>

	<bean id="folder2HandyWorker1" class="domain.Folder">
		<property name="name" value="outBox" />
		<property name="system" value="true" />
		<property name="parentFolder" ref="folder2HandyWorker1" />
		<property name="actor" ref="handyWorker1" />
	</bean>


	<bean id="folder3HandyWorker1" class="domain.Folder">
		<property name="name" value="trashBox" />
		<property name="system" value="true" />
		<property name="parentFolder" ref="folder3HandyWorker1" />
		<property name="actor" ref="handyWorker1" />
	</bean>


	<bean id="folder4HandyWorker1" class="domain.Folder">
		<property name="name" value="spamBox" />
		<property name="system" value="true" />
		<property name="parentFolder" ref="folder4HandyWorker1" />
		<property name="actor" ref="handyWorker1" />
	</bean>


	<!--folders del HandyWorker2 -->

	<bean id="folder1HandyWorker2" class="domain.Folder">
		<property name="name" value="inBox" />
		<property name="system" value="true" />
		<property name="parentFolder" ref="folder1HandyWorker2" />
		<property name="actor" ref="handyWorker2" />
	</bean>

	<bean id="folder2HandyWorker2" class="domain.Folder">
		<property name="name" value="outBox" />
		<property name="system" value="true" />
		<property name="parentFolder" ref="folder2HandyWorker2" />
		<property name="actor" ref="handyWorker2" />
	</bean>

	<bean id="folder3HandyWorker2" class="domain.Folder">
		<property name="name" value="trashBox" />
		<property name="system" value="true" />
		<property name="parentFolder" ref="folder3HandyWorker2" />
		<property name="actor" ref="handyWorker2" />
	</bean>

	<bean id="folder4HandyWorker2" class="domain.Folder">
		<property name="name" value="spamBox" />
		<property name="system" value="true" />
		<property name="parentFolder" ref="folder4HandyWorker2" />
		<property name="actor" ref="handyWorker2" />
	</bean>

	<!--folders del HandyWorker3 -->

	<bean id="folder1HandyWorker3" class="domain.Folder">
		<property name="name" value="inBox" />
		<property name="system" value="true" />
		<property name="parentFolder" ref="folder1HandyWorker3" />
		<property name="actor" ref="handyWorker3" />
	</bean>

	<bean id="folder2HandyWorker3" class="domain.Folder">
		<property name="name" value="outBox" />
		<property name="system" value="true" />
		<property name="parentFolder" ref="folder2HandyWorker3" />
		<property name="actor" ref="handyWorker3" />
	</bean>

	<bean id="folder3HandyWorker3" class="domain.Folder">
		<property name="name" value="trashBox" />
		<property name="system" value="true" />
		<property name="parentFolder" ref="folder3HandyWorker3" />
		<property name="actor" ref="handyWorker3" />
	</bean>

	<bean id="folder4HandyWorker3" class="domain.Folder">
		<property name="name" value="spamBox" />
		<property name="system" value="true" />
		<property name="parentFolder" ref="folder4HandyWorker3" />
		<property name="actor" ref="handyWorker3" />
	</bean>

	<!--folders del HandyWorker4 -->

	<bean id="folder1HandyWorker4" class="domain.Folder">
		<property name="name" value="inBox" />
		<property name="system" value="true" />
		<property name="parentFolder" ref="folder1HandyWorker4" />
		<property name="actor" ref="handyWorker4" />
	</bean>

	<bean id="folder2HandyWorker4" class="domain.Folder">
		<property name="name" value="outBox" />
		<property name="system" value="true" />
		<property name="parentFolder" ref="folder2HandyWorker4" />
		<property name="actor" ref="handyWorker4" />
	</bean>


	<bean id="folder3HandyWorker4" class="domain.Folder">
		<property name="name" value="trashBox" />
		<property name="system" value="true" />
		<property name="parentFolder" ref="folder3HandyWorker4" />
		<property name="actor" ref="handyWorker4" />
	</bean>


	<bean id="folder4HandyWorker4" class="domain.Folder">
		<property name="name" value="spamBox" />
		<property name="system" value="true" />
		<property name="parentFolder" ref="folder4HandyWorker4" />
		<property name="actor" ref="handyWorker4" />
	</bean>

	<!-- folders del administrator1 -->

	<bean id="folder1Administrator1" class="domain.Folder">
		<property name="name" value="inBox" />
		<property name="system" value="true" />
		<property name="parentFolder" ref="folder1Administrator1" />
		<property name="actor" ref="administrator1" />
	</bean>

	<bean id="folder2Administrator1" class="domain.Folder">
		<property name="name" value="outBox" />
		<property name="system" value="true" />
		<property name="parentFolder" ref="folder2Administrator1" />
		<property name="actor" ref="administrator1" />
	</bean>

	<bean id="folder3Administrator1" class="domain.Folder">
		<property name="name" value="trashBox" />
		<property name="system" value="true" />
		<property name="parentFolder" ref="folder3Administrator1" />
		<property name="actor" ref="administrator1" />
	</bean>


	<bean id="folder4Administrator1" class="domain.Folder">
		<property name="name" value="spamBox" />
		<property name="system" value="true" />
		<property name="parentFolder" ref="folder4Administrator1" />
		<property name="actor" ref="administrator1" />
	</bean>




	<!-- folders del administrator2 -->

	<bean id="folder1Administrator2" class="domain.Folder">
		<property name="name" value="inBox" />
		<property name="system" value="true" />
		<property name="parentFolder" ref="folder1Administrator2" />
		<property name="actor" ref="administrator2" />
	</bean>

	<bean id="folder2Administrator2" class="domain.Folder">
		<property name="name" value="outBox" />
		<property name="system" value="true" />
		<property name="parentFolder" ref="folder2Administrator2" />
		<property name="actor" ref="administrator2" />
	</bean>

	<bean id="folder3Administrator2" class="domain.Folder">
		<property name="name" value="trashBox" />
		<property name="system" value="true" />
		<property name="parentFolder" ref="folder3Administrator2" />
		<property name="actor" ref="administrator2" />
	</bean>

	<bean id="folder4Administrator2" class="domain.Folder">
		<property name="name" value="spamBox" />
		<property name="system" value="true" />
		<property name="parentFolder" ref="folder4Administrator2" />
		<property name="actor" ref="administrator2" />
	</bean>


	<!-- __________________________Settings_______________________________________________  -->
		
		<bean id="settings1" class="domain.Settings"> 
			<property name="systemName" value="Acme Handy Worker"></property> 
			<property name="banner" value="https://tinyurl.com/acme-handy-worker-logo"></property> 
			<property name="welcomeMessageEnglish" value="Welcome to Acme Handy Worker! Price, quality, and trust in a single place"></property> 
			<property name="welcomeMessageSpanish" value="¡Bienvenidos a Acme Handy Worker! Precio, calidad y confianza en el mismo sitio"></property>
			<property name="spamWords">
				<list>
					<value>sex</value>
					<value>viagra</value>
					<value>cialis</value>
					<value>one million</value>
					<value>you've been selected</value>
					<value>Nigeria</value>
					<value>sexo</value>
					<value>un millón</value>
					<value>ha sido seleccionado</value>
				</list>
			</property> 
			<property name="vat" value="21"></property> 
			<property name="countryCode" value="+34"></property> 
			<property name="creditCardMakes">
				<list>
					<value>VISA</value>
					<value>MASTER</value>
					<value>DINNERS</value>
					<value>AMEX</value>
				</list>
			</property> 
			<property name="finderCacheHours" value="1"></property> 
			<property name="maxCacheResults" value="10"></property> 
			<property name="positiveWords">
				<list>
					<value>good</value>
					<value>fantastic</value>
					<value>excellent</value>
					<value>great</value>
					<value>amazing</value>
					<value>terrific</value>
					<value>beautiful</value>
					<value>bueno</value>
					<value>fantástico</value>
					<value>buena</value>
					<value>fantástica</value>
					<value>excelente</value>
					<value>gran</value>
					<value>increíble</value>
					<value>terrorífico</value>
					<value>hermoso</value>
					<value>terrorífica</value>
					<value>hermosa</value>
				</list>
			</property> 
			<property name="negativeWords">
				<list>
					<value>not</value>
					<value>bad</value>
					<value>horrible</value>
					<value>average</value>
					<value>disaster</value>
					<value>no</value>
					<value>malo</value>
					<value>mala</value>
					<value>horrible</value>
					<value>mediocre</value>
					<value>desastre</value>
				</list>
			</property> 
		</bean>

	<!-- _______________________________SocialProfile________________________________________________ -->
	<bean id="socialProfile1" class="domain.SocialProfile">
		<property name="nick" value="Manolete"></property>
		<property name="networkName" value="Twitter"></property>
		<property name="actor" ref="handyWorker1" />
		<property name="profile" value="https://profile.es/"></property>
	</bean>

	<bean id="socialProfile2" class="domain.SocialProfile">
		<property name="nick" value="Manolete2"></property>
		<property name="networkName" value="Twitter"></property>
		<property name="actor" ref="handyWorker2" />
		<property name="profile" value="https://profile.es/"></property>
	</bean>

	<bean id="socialProfile3" class="domain.SocialProfile">
		<property name="nick" value="Manolete3"></property>
		<property name="networkName" value="Twitter"></property>
		<property name="actor" ref="handyWorker3" />
		<property name="profile" value="https://profile.es/"></property>
	</bean>

	<bean id="socialProfile1Admin1" class="domain.SocialProfile">
		<property name="nick" value="Manolete4"></property>
		<property name="networkName" value="Twitter"></property>
		<property name="actor" ref="administrator1" />
		<property name="profile" value="https://profile.es/"></property>
	</bean>

	<bean id="socialProfile2Admin1" class="domain.SocialProfile">
		<property name="nick" value="Manolete5"></property>
		<property name="networkName" value="Twitter"></property>
		<property name="actor" ref="administrator1" />
		<property name="profile" value="https://profile.es/"></property>
	</bean>

<bean id="socialProfileCustomer1" class="domain.SocialProfile">
		<property name="nick" value="Alfonso"></property>
		<property name="networkName" value="Twitter"></property>
		<property name="actor" ref="customer1" />
		<property name="profile" value="https://profile.es/"></property>
	</bean>
	
	<bean id="socialProfile2Customer1" class="domain.SocialProfile">
		<property name="nick" value="AlfonsoFB"></property>
		<property name="networkName" value="Facebook"></property>
		<property name="actor" ref="customer1" />
		<property name="profile" value="https://profile.es/"></property>
	</bean>
	
	<bean id="socialProfile3Customer1" class="domain.SocialProfile">
		<property name="nick" value="Alfonsito_guapete"></property>
		<property name="networkName" value="Tinder"></property>
		<property name="actor" ref="customer1" />
		<property name="profile" value="https://profile.es/"></property>
	</bean>

	<bean id="socialProfile4Customer1" class="domain.SocialProfile">
		<property name="nick" value="Alfonsitx"></property>
		<property name="networkName" value="Tumblr"></property>
		<property name="actor" ref="customer1" />
		<property name="profile" value="https://profile.es/"></property>
	</bean>

	<!-- _______________________________________HANDYWORKER ______________________________________________ -->


	<bean id="handyWorker1" class="domain.HandyWorker">
		<property name="name" value="Antonio"></property>
		<property name="middleName" value="Grinch"></property>
		<property name="surname" value="Papp"></property>
		<property name="photo"
			value="https://www.cinetecamadrid.com/sites/default/files/activity/image/imagen_EL_GRINCH00_0.jpg"></property>
		<property name="email" value="elgrinch@hotmail.com"></property>
		<property name="phone" value="+34(456)123456754"></property>
		<property name="address" value="C/ Polo Norte"></property>
		<property name="suspicious" value="false"></property>
		<property name="score" value="0.95"></property>
		<property name="userAccount" ref="userAccount14"></property>
		<property name="make" value="Antonio Grinch Papp"></property>
	</bean>

	<bean id="handyWorker2" class="domain.HandyWorker">
		<property name="name" value="Luis"></property>
		<property name="middleName" value="Pokemaniako"></property>
		<property name="surname" value="Zumarraga"></property>
		<property name="photo"
			value="https://cdn.memegenerator.es/imagenes/memes/full/16/43/16433834.jpg"></property>
		<property name="email" value="pokeluisito@hotmail.com"></property>
		<property name="phone" value="+34(456)123456753"></property>
		<property name="address" value="C/ Rataland"></property>
		<property name="suspicious" value="false"></property>
		<property name="score" value="0.85"></property>
		<property name="userAccount" ref="userAccount8"></property>
		<property name="make" value="Luis Pokemaniako Zumarraga"></property>
	</bean>

	<bean id="handyWorker3" class="domain.HandyWorker">
		<property name="name" value="Javi"></property>
		<property name="middleName" value="Rmano"></property>
		<property name="surname" value="Camunia"></property>
		<property name="photo"
			value="https://misanimales.com/wp-content/uploads/2018/05/curiosidades-del-perezoso.jpg"></property>
		<property name="email" value="camunon@hotmail.com"></property>
		<property name="phone" value="+34(456)123456752"></property>
		<property name="address" value="C/ Lovaina"></property>
		<property name="suspicious" value="false"></property>
		<property name="score" value="0.75"></property>
		<property name="userAccount" ref="userAccount9">
		</property>
		<property name="make" value="Javi Rmano Camunia"></property>
	</bean>

	<bean id="handyWorker4" class="domain.HandyWorker">
		<property name="name" value="Tobias"></property>
		<property name="middleName" value="Elpen"></property>
		<property name="surname" value="Feliz"></property>
		<property name="photo"
			value="https://www.peluchetes.com/contenido/uploads/2015/08/peluche-perro-salchicha.jpg"></property>
		<property name="email" value="tobi@hotmail.com"></property>
		<property name="phone" value="+34(456)123456751"></property>
		<property name="address" value="C/ Reja"></property>
		<property name="suspicious" value="false"></property>
		<property name="score" value="0.66"></property>
		<property name="userAccount" ref="userAccount10"></property>
		<property name="make" value="Tobias Elpen Feliz"></property>
	</bean>



	<!--__________________________MESSAGES _________________________________ -->




	<!-- message1 ====> HW1 TO CUST1 -->

	<bean id="message1" class="domain.Message">
		<property name="moment" value="July 12, 2017 12:00"></property>
		<property name="subject" value="Asunto1"></property>
		<property name="body" value="Cuerpo del mensaje 1"></property>
		<property name="priority" value="NEUTRAL"></property>
		<property name="tags">
			<list></list>
		</property>
		<property name="folder">
			<ref bean="folder1Customer1" />
		</property>
		<property name="sender" ref="handyWorker1"></property>
		<property name="receiver" ref="customer1"></property>
	</bean>
	
	<bean id="message1b" class="domain.Message">
		<property name="moment" value="July 12, 2017 12:00"></property>
		<property name="subject" value="Asunto1"></property>
		<property name="body" value="Cuerpo del mensaje 1"></property>
		<property name="priority" value="NEUTRAL"></property>
		<property name="tags">
			<list></list>
		</property>
		<property name="folder">
			<ref bean="folder2HandyWorker1" />
		</property>
		<property name="sender" ref="handyWorker1"></property>
		<property name="receiver" ref="customer1"></property>
	</bean>


	<!-- message2 ====> CUST2 TO HW2 -->

	<bean id="message2" class="domain.Message">
		<property name="moment" value="July 13, 2017 12:00"></property>
		<property name="subject" value="Asunto2"></property>
		<property name="body" value="Cuerpo del mensaje 2"></property>
		<property name="priority" value="HIGH"></property>
		<property name="tags">
			<list></list>
		</property>
		<property name="folder">
			<ref bean="folder1HandyWorker2" />
		</property>
		<property name="sender" ref="customer2"></property>
		<property name="receiver" ref="handyWorker2"></property>

	</bean>
	
	<bean id="message2b" class="domain.Message">
		<property name="moment" value="July 13, 2017 12:00"></property>
		<property name="subject" value="Asunto2"></property>
		<property name="body" value="Cuerpo del mensaje 2"></property>
		<property name="priority" value="HIGH"></property>
		<property name="tags">
			<list></list>
		</property>
		<property name="folder">
			<ref bean="folder2Customer2" />
		</property>
		<property name="sender" ref="customer2"></property>
		<property name="receiver" ref="handyWorker2"></property>

	</bean>

	<!-- message3 ====> CUST3 TO HW3 -->

	<bean id="message3" class="domain.Message">
		<property name="moment" value="July 14, 2017 12:00"></property>
		<property name="subject" value="Asunto3"></property>
		<property name="body" value="Cuerpo del mensaje 3"></property>
		<property name="priority" value="LOW"></property>
		<property name="tags">
			<list></list>
		</property>
		<property name="folder">
			<ref bean="folder1HandyWorker3" />
		</property>
		<property name="sender" ref="customer3"></property>
		<property name="receiver" ref="handyWorker3"></property>

	</bean>

	<bean id="message3b" class="domain.Message">
		<property name="moment" value="July 14, 2017 12:00"></property>
		<property name="subject" value="Asunto3"></property>
		<property name="body" value="Cuerpo del mensaje 3"></property>
		<property name="priority" value="LOW"></property>
		<property name="tags">
			<list></list>
		</property>
		<property name="folder">
			<ref bean="folder2Customer3" />
		</property>
		<property name="sender" ref="customer3"></property>
		<property name="receiver" ref="handyWorker3"></property>

	</bean>
 	
</beans>
